{"container_type": "Author", "filled": ["basics", "indices", "counts", "coauthors", "publications", "public_access"], "source": "SEARCH_AUTHOR_SNIPPETS", "scholar_id": "aorQUi0AAAAJ", "url_picture": "https://scholar.google.com/citations?view_op=medium_photo&user=aorQUi0AAAAJ", "name": "Svetlana Obraztsova", "affiliation": "Nanyang Technological University", "email_domain": "@ntu.edu.sg", "interests": ["computational social choice"], "citedby": 657, "organization": 3012140508424117850, "homepage": null, "citedby5y": 444, "hindex": 12, "hindex5y": 12, "i10index": 20, "i10index5y": 16, "cites_per_year": {"2011": 8, "2012": 19, "2013": 13, "2014": 22, "2015": 57, "2016": 84, "2017": 65, "2018": 66, "2019": 98, "2020": 59, "2021": 92, "2022": 62}, "coauthors": [{"container_type": "Author", "filled": [], "scholar_id": "JwJRnmAAAAAJ", "source": "CO_AUTHORS_LIST", "name": "Zinovi Rabinovich", "affiliation": "Nanyang Technological University"}, {"container_type": "Author", "filled": [], "scholar_id": "MsGRzsoAAAAJ", "source": "CO_AUTHORS_LIST", "name": "Edith Elkind", "affiliation": "University of Oxford"}, {"container_type": "Author", "filled": [], "scholar_id": "nL-zXO4AAAAJ", "source": "CO_AUTHORS_LIST", "name": "Maria Polukarov", "affiliation": "Department of Informatics, King's College London"}, {"container_type": "Author", "filled": [], "scholar_id": "YO7cKNMAAAAJ", "source": "CO_AUTHORS_LIST", "name": "Jeffrey S. Rosenschein", "affiliation": "Professor of Computer Science, Hebrew University"}, {"container_type": "Author", "filled": [], "scholar_id": "VDyjbagAAAAJ", "source": "CO_AUTHORS_LIST", "name": "Evangelos Markakis", "affiliation": "Athens University of Economics and Business"}, {"container_type": "Author", "filled": [], "scholar_id": "LTMdHpwAAAAJ", "source": "CO_AUTHORS_LIST", "name": "Omer Lev", "affiliation": "Ben-Gurion University"}, {"container_type": "Author", "filled": [], "scholar_id": "UM0rCaoAAAAJ", "source": "CO_AUTHORS_LIST", "name": "Lihi (Naamani) Dery", "affiliation": "Senior Lecturer, Industrial Engineering and Management, Ariel University"}, {"container_type": "Author", "filled": [], "scholar_id": "FX5CsuYAAAAJ", "source": "CO_AUTHORS_LIST", "name": "Nick Jennings", "affiliation": "Vice-Chancellor and President, Loughborough University"}, {"container_type": "Author", "filled": [], "scholar_id": "32F7YzcAAAAJ", "source": "CO_AUTHORS_LIST", "name": "Piotr Faliszewski", "affiliation": "AGH University of Science and Technology"}, {"container_type": "Author", "filled": [], "scholar_id": "gszGlZIAAAAJ", "source": "CO_AUTHORS_LIST", "name": "Wei Qiu", "affiliation": "Nanyang Technological University"}, {"container_type": "Author", "filled": [], "scholar_id": "PEEpuNwAAAAJ", "source": "CO_AUTHORS_LIST", "name": "Bo An", "affiliation": "Nanyang Technological University"}, {"container_type": "Author", "filled": [], "scholar_id": "HKy4T5kAAAAJ", "source": "CO_AUTHORS_LIST", "name": "Piotr Skowron", "affiliation": "University of Warsaw"}, {"container_type": "Author", "filled": [], "scholar_id": "UHZ0XFoAAAAJ", "source": "CO_AUTHORS_LIST", "name": "David RM Thompson", "affiliation": "Google"}, {"container_type": "Author", "filled": [], "scholar_id": "Bb-VR9sAAAAJ", "source": "CO_AUTHORS_LIST", "name": "Noam Hazon", "affiliation": "Senior Lecturer, Ariel University"}, {"container_type": "Author", "filled": [], "scholar_id": "JzG5teMAAAAJ", "source": "CO_AUTHORS_LIST", "name": "Alexander Karpov", "affiliation": "Higher School of Economics"}, {"container_type": "Author", "filled": [], "scholar_id": "qKmgGU0AAAAJ", "source": "CO_AUTHORS_LIST", "name": "Ulle Endriss", "affiliation": "ILLC, University of Amsterdam"}, {"container_type": "Author", "filled": [], "scholar_id": "JEVpgE8AAAAJ", "source": "CO_AUTHORS_LIST", "name": "Rundong Wang", "affiliation": "Ph.D. student of Computer Science, Nanyang Technological University"}, {"container_type": "Author", "filled": [], "scholar_id": "m0PW6DQAAAAJ", "source": "CO_AUTHORS_LIST", "name": "Yair Zick", "affiliation": "University of Massachusetts, Amherst"}, {"container_type": "Author", "filled": [], "scholar_id": "vo5iW3wAAAAJ", "source": "CO_AUTHORS_LIST", "name": "Meir Kalech", "affiliation": "Ben-Gurion University"}, {"container_type": "Author", "filled": [], "scholar_id": "Tk65Z3gAAAAJ", "source": "CO_AUTHORS_LIST", "name": "Martin Lackner", "affiliation": "TU Wien"}, {"container_type": "Author", "filled": [], "scholar_id": "YL5djpEAAAAJ", "source": "CO_AUTHORS_LIST", "name": "Alexandros A. Voudouris", "affiliation": "CSEE, University of Essex"}, {"container_type": "Author", "filled": [], "scholar_id": "egv-am4AAAAJ", "source": "CO_AUTHORS_LIST", "name": "Arkadii Slinko", "affiliation": "Department of Mathematics and Centre for Mathematics in Social Sciences, The University \u2026"}, {"container_type": "Author", "filled": [], "scholar_id": "zFDLf0UAAAAJ", "source": "CO_AUTHORS_LIST", "name": "Dimitris Fotakis", "affiliation": "Associate Professor, Electrical & Computer Eng., NTU Athens"}, {"container_type": "Author", "filled": [], "scholar_id": "Xda5bmoAAAAJ", "source": "CO_AUTHORS_LIST", "name": "Thodoris Lykouris", "affiliation": "MIT"}, {"container_type": "Author", "filled": [], "scholar_id": "oz_SBAMAAAAJ", "source": "CO_AUTHORS_LIST", "name": "Zoi Terzopoulou", "affiliation": "postdoctoral researcher, University Paris-Dauphine"}, {"container_type": "Author", "filled": [], "scholar_id": "jWi-5AYAAAAJ", "source": "CO_AUTHORS_LIST", "name": "Chai Kiat Yeo", "affiliation": "Nanyang Technological University"}, {"container_type": "Author", "filled": [], "scholar_id": "-Gw8VRMAAAAJ", "source": "CO_AUTHORS_LIST", "name": "Reshef Meir", "affiliation": "Associate Prof., Technion-Israel Inst. of Technology"}, {"container_type": "Author", "filled": [], "scholar_id": "DdtpTRwAAAAJ", "source": "CO_AUTHORS_LIST", "name": "Robert Bredereck", "affiliation": "TU Clausthal"}, {"container_type": "Author", "filled": [], "scholar_id": "dSfOjCQAAAAJ", "source": "CO_AUTHORS_LIST", "name": "Nimrod Talmon", "affiliation": "Ben-Gurion University"}, {"container_type": "Author", "filled": [], "scholar_id": "guvQn0EAAAAJ", "source": "CO_AUTHORS_LIST", "name": "Jiehua Chen", "affiliation": "TU Vienna"}, {"container_type": "Author", "filled": [], "scholar_id": "K2BY6JcAAAAJ", "source": "CO_AUTHORS_LIST", "name": "Rolf Niedermeier", "affiliation": "TU Berlin"}, {"container_type": "Author", "filled": [], "scholar_id": "OIQwi7oAAAAJ", "source": "CO_AUTHORS_LIST", "name": "Alan Tsang", "affiliation": "Carleton University"}, {"container_type": "Author", "filled": [], "scholar_id": "3bhoIywAAAAJ", "source": "CO_AUTHORS_LIST", "name": "Judy Goldsmith", "affiliation": "University of Kentucky"}, {"container_type": "Author", "filled": [], "scholar_id": "cNgZXNcAAAAJ", "source": "CO_AUTHORS_LIST", "name": "Jerome Lang", "affiliation": "senior researcher at CNRS"}, {"container_type": "Author", "filled": [], "scholar_id": "aTh7cOcAAAAJ", "source": "CO_AUTHORS_LIST", "name": "Nicolas Maudet", "affiliation": "LIP6, Sorbonne Universit\u00e9"}, {"container_type": "Author", "filled": [], "scholar_id": "XkQky2MAAAAJ", "source": "CO_AUTHORS_LIST", "name": "Amr ALHOSSARY", "affiliation": "Wesleyan University"}, {"container_type": "Author", "filled": [], "scholar_id": "ptI-HHkAAAAJ", "source": "CO_AUTHORS_LIST", "name": "Yevgeniy Vorobeychik", "affiliation": "Washington University in Saint Louis"}], "publications": [{"container_type": "Publication", "source": "AUTHOR_PUBLICATION_ENTRY", "bib": {"title": "Ties matter: Complexity of voting manipulation revisited", "pub_year": "2011", "citation": "Twenty-second International Joint conference on artificial Intelligence, 2011"}, "filled": false, "author_pub_id": "aorQUi0AAAAJ:u5HHmVD_uO8C", "num_citations": 63, "citedby_url": "https://scholar.google.com/scholar?oi=bibs&hl=en&cites=12401460775725504507", "cites_id": ["12401460775725504507"], "public_access": null}, {"container_type": "Publication", "source": "AUTHOR_PUBLICATION_ENTRY", "bib": {"title": "On the convergence of iterative voting: how restrictive should restricted dynamics be?", "pub_year": "2015", "citation": "Proceedings of the AAAI conference on artificial intelligence 29 (1), 2015"}, "filled": false, "author_pub_id": "aorQUi0AAAAJ:8k81kl-MbHgC", "num_citations": 59, "citedby_url": "https://scholar.google.com/scholar?oi=bibs&hl=en&cites=6517725442705282563", "cites_id": ["6517725442705282563"], "public_access": true}, {"container_type": "Publication", "source": "AUTHOR_PUBLICATION_ENTRY", "bib": {"title": "Plurality voting with truth-biased agents", "pub_year": "2013", "citation": "International Symposium on Algorithmic Game Theory, 26-37, 2013"}, "filled": false, "author_pub_id": "aorQUi0AAAAJ:_FxGoFyzp5QC", "num_citations": 50, "citedby_url": "https://scholar.google.com/scholar?oi=bibs&hl=en&cites=7413833619383473902,15402290069026847051", "cites_id": ["7413833619383473902", "15402290069026847051"], "public_access": null}, {"container_type": "Publication", "source": "AUTHOR_PUBLICATION_ENTRY", "bib": {"title": "On the complexity of voting manipulation under randomized tie-breaking", "pub_year": "2011", "citation": "Twenty-Second International Joint Conference on Artificial Intelligence, 2011"}, "filled": false, "author_pub_id": "aorQUi0AAAAJ:u-x6o8ySG0sC", "num_citations": 46, "citedby_url": "https://scholar.google.com/scholar?oi=bibs&hl=en&cites=13319747327290640707,14811906507757773380", "cites_id": ["13319747327290640707", "14811906507757773380"], "public_access": null}, {"container_type": "Publication", "source": "AUTHOR_PUBLICATION_ENTRY", "bib": {"title": "Analysis of equilibria in iterative voting schemes", "pub_year": "2015", "citation": "Twenty-Ninth AAAI Conference on Artificial Intelligence, 2015"}, "filled": false, "author_pub_id": "aorQUi0AAAAJ:Se3iqnhoufwC", "num_citations": 45, "citedby_url": "https://scholar.google.com/scholar?oi=bibs&hl=en&cites=11561753879208141752", "cites_id": ["11561753879208141752"], "public_access": true}, {"container_type": "Publication", "source": "AUTHOR_PUBLICATION_ENTRY", "bib": {"title": "Strategic voting with incomplete information", "pub_year": "2016", "citation": "AAAI Press/International Joint Conferences on Artificial Intelligence, 2016"}, "filled": false, "author_pub_id": "aorQUi0AAAAJ:9ZlFYXVOiuMC", "num_citations": 40, "citedby_url": "https://scholar.google.com/scholar?oi=bibs&hl=en&cites=8989285009623700584", "cites_id": ["8989285009623700584"], "public_access": true}, {"container_type": "Publication", "source": "AUTHOR_PUBLICATION_ENTRY", "bib": {"title": "Optimal manipulation of voting rules", "pub_year": "2012", "citation": "Twenty-Sixth AAAI Conference on Artificial Intelligence, 2012"}, "filled": false, "author_pub_id": "aorQUi0AAAAJ:d1gkVwhDpl0C", "num_citations": 30, "citedby_url": "https://scholar.google.com/scholar?oi=bibs&hl=en&cites=16396386887054238511", "cites_id": ["16396386887054238511"], "public_access": null}, {"container_type": "Publication", "source": "AUTHOR_PUBLICATION_ENTRY", "bib": {"title": "On manipulation in multi-winner elections based on scoring rules", "pub_year": "2013", "citation": "Proceedings of the 2013 international conference on Autonomous agents and \u2026, 2013"}, "filled": false, "author_pub_id": "aorQUi0AAAAJ:eQOLeE2rZwMC", "num_citations": 27, "citedby_url": "https://scholar.google.com/scholar?oi=bibs&hl=en&cites=14328333084963490799", "cites_id": ["14328333084963490799"], "public_access": null}, {"container_type": "Publication", "source": "AUTHOR_PUBLICATION_ENTRY", "bib": {"title": "The complexity of recognizing incomplete single-crossing preferences", "pub_year": "2015", "citation": "Proceedings of the AAAI Conference on Artificial Intelligence 29 (1), 2015"}, "filled": false, "author_pub_id": "aorQUi0AAAAJ:5nxA0vEk-isC", "num_citations": 23, "citedby_url": "https://scholar.google.com/scholar?oi=bibs&hl=en&cites=2416917861881647673,13195266856879570320", "cites_id": ["2416917861881647673", "13195266856879570320"], "public_access": true}, {"container_type": "Publication", "source": "AUTHOR_PUBLICATION_ENTRY", "bib": {"title": "Equilibria of plurality voting: Lazy and truth-biased voters", "pub_year": "2015", "citation": "International Symposium on Algorithmic Game Theory, 110-122, 2015"}, "filled": false, "author_pub_id": "aorQUi0AAAAJ:hqOjcs7Dif8C", "num_citations": 22, "citedby_url": "https://scholar.google.com/scholar?oi=bibs&hl=en&cites=10309737148307384860", "cites_id": ["10309737148307384860"], "public_access": null}, {"container_type": "Publication", "source": "AUTHOR_PUBLICATION_ENTRY", "bib": {"title": "Doodle poll games", "pub_year": "2017", "citation": "Association for Computing Machinery, 2017"}, "filled": false, "author_pub_id": "aorQUi0AAAAJ:4DMP91E08xMC", "num_citations": 21, "citedby_url": "https://scholar.google.com/scholar?oi=bibs&hl=en&cites=1236694586240619744", "cites_id": ["1236694586240619744"], "public_access": true}, {"container_type": "Publication", "source": "AUTHOR_PUBLICATION_ENTRY", "bib": {"title": "Variations on the hotelling-downs model", "pub_year": "2016", "citation": "Thirtieth AAAI Conference on Artificial Intelligence, 2016"}, "filled": false, "author_pub_id": "aorQUi0AAAAJ:mVmsd5A6BfQC", "num_citations": 21, "citedby_url": "https://scholar.google.com/scholar?oi=bibs&hl=en&cites=12710070116786187474", "cites_id": ["12710070116786187474"], "public_access": true}, {"container_type": "Publication", "source": "AUTHOR_PUBLICATION_ENTRY", "bib": {"title": "RMIX: Learning risk-sensitive policies for cooperative reinforcement learning agents", "pub_year": "2021", "citation": "Advances in Neural Information Processing Systems 34, 23049-23062, 2021"}, "filled": false, "author_pub_id": "aorQUi0AAAAJ:NMxIlDl6LWMC", "num_citations": 12, "citedby_url": "https://scholar.google.com/scholar?oi=bibs&hl=en&cites=708580131812596815", "cites_id": ["708580131812596815"], "public_access": null}, {"container_type": "Publication", "source": "AUTHOR_PUBLICATION_ENTRY", "bib": {"title": "Convergence to equilibria in strategic candidacy", "pub_year": "2015", "citation": "Twenty-Fourth International Joint Conference on Artificial Intelligence, 2015"}, "filled": false, "author_pub_id": "aorQUi0AAAAJ:YOwf2qJgpHMC", "num_citations": 12, "citedby_url": "https://scholar.google.com/scholar?oi=bibs&hl=en&cites=7590824152662826589", "cites_id": ["7590824152662826589"], "public_access": true}, {"container_type": "Publication", "source": "AUTHOR_PUBLICATION_ENTRY", "bib": {"title": "Protecting elections by recounting ballots", "pub_year": "2021", "citation": "Artificial Intelligence 290, 103401, 2021"}, "filled": false, "author_pub_id": "aorQUi0AAAAJ:4JMBOYKVnBMC", "num_citations": 11, "citedby_url": "https://scholar.google.com/scholar?oi=bibs&hl=en&cites=7751208118014147984", "cites_id": ["7751208118014147984"], "public_access": true}, {"container_type": "Publication", "source": "AUTHOR_PUBLICATION_ENTRY", "bib": {"title": "Lie on the fly: Strategic voting in an iterative preference elicitation process", "pub_year": "2019", "citation": "Group Decision and Negotiation 28 (6), 1077-1107, 2019"}, "filled": false, "author_pub_id": "aorQUi0AAAAJ:e5wmG9Sq2KIC", "num_citations": 11, "citedby_url": "https://scholar.google.com/scholar?oi=bibs&hl=en&cites=8292916066746633509,9460630282040035617", "cites_id": ["8292916066746633509", "9460630282040035617"], "public_access": null}, {"container_type": "Publication", "source": "AUTHOR_PUBLICATION_ENTRY", "bib": {"title": "Strategic candidacy games with lazy candidates", "pub_year": "2015", "citation": "Twenty-Fourth International Joint Conference on Artificial Intelligence, 2015"}, "filled": false, "author_pub_id": "aorQUi0AAAAJ:_kc_bZDykSQC", "num_citations": 11, "citedby_url": "https://scholar.google.com/scholar?oi=bibs&hl=en&cites=2970333179179300879", "cites_id": ["2970333179179300879"], "public_access": true}, {"container_type": "Publication", "source": "AUTHOR_PUBLICATION_ENTRY", "bib": {"title": "Trembling hand equilibria of plurality voting", "pub_year": "2016", "citation": "AAAI Press/International Joint Conferences on Artificial Intelligence, 2016"}, "filled": false, "author_pub_id": "aorQUi0AAAAJ:dhFuZR0502QC", "num_citations": 10, "citedby_url": "https://scholar.google.com/scholar?oi=bibs&hl=en&cites=5118801213909055831", "cites_id": ["5118801213909055831"], "public_access": true}, {"container_type": "Publication", "source": "AUTHOR_PUBLICATION_ENTRY", "bib": {"title": "Beyond plurality: Truth-bias in binary scoring rules", "pub_year": "2015", "citation": "International Conference on Algorithmic Decision Theory, 451-468, 2015"}, "filled": false, "author_pub_id": "aorQUi0AAAAJ:Zph67rFs4hoC", "num_citations": 10, "citedby_url": "https://scholar.google.com/scholar?oi=bibs&hl=en&cites=6728644454995210750", "cites_id": ["6728644454995210750"], "public_access": null}, {"container_type": "Publication", "source": "AUTHOR_PUBLICATION_ENTRY", "bib": {"title": "On swap-distance geometry of voting rules", "pub_year": "2013", "citation": "Proceedings of the 2013 international conference on Autonomous agents and \u2026, 2013"}, "filled": false, "author_pub_id": "aorQUi0AAAAJ:ufrVoPGSRksC", "num_citations": 10, "citedby_url": "https://scholar.google.com/scholar?oi=bibs&hl=en&cites=6077127669018655754", "cites_id": ["6077127669018655754"], "public_access": null}, {"container_type": "Publication", "source": "AUTHOR_PUBLICATION_ENTRY", "bib": {"title": "Nonmyopic voting dynamics: An optimistic approach", "pub_year": "2016", "citation": "Proceedings of the10th Multidisciplinary Workshop on Advances in Preference \u2026, 2016"}, "filled": false, "author_pub_id": "aorQUi0AAAAJ:7PzlFSSx8tAC", "num_citations": 9, "citedby_url": "https://scholar.google.com/scholar?oi=bibs&hl=en&cites=14720093925002127592", "cites_id": ["14720093925002127592"], "public_access": null}, {"container_type": "Publication", "source": "AUTHOR_PUBLICATION_ENTRY", "bib": {"title": "Farsighted voting dynamics", "pub_year": "2015", "citation": "AGT@ IJCAI workshop, Buenos Aires, Argentina, 2015"}, "filled": false, "author_pub_id": "aorQUi0AAAAJ:qxL8FJ1GzNcC", "num_citations": 9, "citedby_url": "https://scholar.google.com/scholar?oi=bibs&hl=en&cites=693817248122343182", "cites_id": ["693817248122343182"], "public_access": true}, {"container_type": "Publication", "source": "AUTHOR_PUBLICATION_ENTRY", "bib": {"title": "Restricted domains of dichotomous preferences with possibly incomplete information", "pub_year": "2021", "citation": "Proceedings of the AAAI Conference on Artificial Intelligence 35 (6), 5726-5733, 2021"}, "filled": false, "author_pub_id": "aorQUi0AAAAJ:maZDTaKrznsC", "num_citations": 8, "citedby_url": "https://scholar.google.com/scholar?oi=bibs&hl=en&cites=2784293911859654041", "cites_id": ["2784293911859654041"], "public_access": null}, {"container_type": "Publication", "source": "AUTHOR_PUBLICATION_ENTRY", "bib": {"title": "Real candidacy games: a new model for strategic candidacy", "pub_year": "2017", "citation": "Proceedings of the 16th Conference on Autonomous Agents and MultiAgent \u2026, 2017"}, "filled": false, "author_pub_id": "aorQUi0AAAAJ:hFOr9nPyWt4C", "num_citations": 8, "citedby_url": "https://scholar.google.com/scholar?oi=bibs&hl=en&cites=5603379578789958956", "cites_id": ["5603379578789958956"], "public_access": null}, {"container_type": "Publication", "source": "AUTHOR_PUBLICATION_ENTRY", "bib": {"title": "Influence maximization in switching-selection threshold models", "pub_year": "2014", "citation": "International Symposium on Algorithmic Game Theory, 122-133, 2014"}, "filled": false, "author_pub_id": "aorQUi0AAAAJ:UebtZRa9Y70C", "num_citations": 8, "citedby_url": "https://scholar.google.com/scholar?oi=bibs&hl=en&cites=2002613162506381494", "cites_id": ["2002613162506381494"], "public_access": null}, {"container_type": "Publication", "source": "AUTHOR_PUBLICATION_ENTRY", "bib": {"title": "Distant truth: Bias under vote distortion costs", "pub_year": "2017", "citation": "Proceedings of the 16th Conference on Autonomous Agents and MultiAgent \u2026, 2017"}, "filled": false, "author_pub_id": "aorQUi0AAAAJ:-f6ydRqryjwC", "num_citations": 7, "citedby_url": "https://scholar.google.com/scholar?oi=bibs&hl=en&cites=14369146099191309115", "cites_id": ["14369146099191309115"], "public_access": true}, {"container_type": "Publication", "source": "AUTHOR_PUBLICATION_ENTRY", "bib": {"title": "Complexity of finding equilibria of plurality voting under structured preferences", "pub_year": "2016", "citation": "AAMAS'16: Proceedings of the 2016 International Conference on Autonomous \u2026, 2016"}, "filled": false, "author_pub_id": "aorQUi0AAAAJ:QIV2ME_5wuYC", "num_citations": 7, "citedby_url": "https://scholar.google.com/scholar?oi=bibs&hl=en&cites=2208770824002546729", "cites_id": ["2208770824002546729"], "public_access": true}, {"container_type": "Publication", "source": "AUTHOR_PUBLICATION_ENTRY", "bib": {"title": "The complexity of election problems with group-separable preferences", "pub_year": "2022", "citation": "Autonomous Agents and Multi-Agent Systems 36 (1), 1-28, 2022"}, "filled": false, "author_pub_id": "aorQUi0AAAAJ:JV2RwH3_ST0C", "num_citations": 6, "citedby_url": "https://scholar.google.com/scholar?oi=bibs&hl=en&cites=11690799959437360955", "cites_id": ["11690799959437360955"], "public_access": null}, {"container_type": "Publication", "source": "AUTHOR_PUBLICATION_ENTRY", "bib": {"title": "Mis-spoke or mis-lead: Achieving Robustness in Multi-Agent Communicative Reinforcement Learning", "pub_year": "2021", "citation": "arXiv preprint arXiv:2108.03803, 2021"}, "filled": false, "author_pub_id": "aorQUi0AAAAJ:BqipwSGYUEgC", "num_citations": 6, "citedby_url": "https://scholar.google.com/scholar?oi=bibs&hl=en&cites=4367964143916056699", "cites_id": ["4367964143916056699"], "public_access": null}, {"container_type": "Publication", "source": "AUTHOR_PUBLICATION_ENTRY", "bib": {"title": "Haste makes waste: A case to favour voting bots", "pub_year": "2017", "citation": "Proceedings of the international conference on web intelligence, 419-425, 2017"}, "filled": false, "author_pub_id": "aorQUi0AAAAJ:HDshCWvjkbEC", "num_citations": 6, "citedby_url": "https://scholar.google.com/scholar?oi=bibs&hl=en&cites=12308617050331691804", "cites_id": ["12308617050331691804"], "public_access": null}, {"container_type": "Publication", "source": "AUTHOR_PUBLICATION_ENTRY", "bib": {"title": "Between fairness and a mistrial: Consensus under a deadline", "pub_year": "2016", "citation": "The 10th workshop on advances in preference handling (M-PREF), 2016"}, "filled": false, "author_pub_id": "aorQUi0AAAAJ:L8Ckcad2t8MC", "num_citations": 6, "citedby_url": "https://scholar.google.com/scholar?oi=bibs&hl=en&cites=12719420937752383577", "cites_id": ["12719420937752383577"], "public_access": null}, {"container_type": "Publication", "source": "AUTHOR_PUBLICATION_ENTRY", "bib": {"title": "Lie on the fly: Manipulative voters under iterative voting centre", "pub_year": "2015", "citation": "Proceedings of the 24th International Joint Conference on Artificial \u2026, 2015"}, "filled": false, "author_pub_id": "aorQUi0AAAAJ:TFP_iSt0sucC", "num_citations": 6, "citedby_url": "https://scholar.google.com/scholar?oi=bibs&hl=en&cites=17479613454884263731", "cites_id": ["17479613454884263731"], "public_access": null}, {"container_type": "Publication", "source": "AUTHOR_PUBLICATION_ENTRY", "bib": {"title": "Manipulating elections by selecting issues", "pub_year": "2020", "citation": "Vanderbilt University, 2020"}, "filled": false, "author_pub_id": "aorQUi0AAAAJ:_Qo2XoVZTnwC", "num_citations": 5, "citedby_url": "https://scholar.google.com/scholar?oi=bibs&hl=en&cites=12319159229292232686", "cites_id": ["12319159229292232686"], "public_access": null}, {"container_type": "Publication", "source": "AUTHOR_PUBLICATION_ENTRY", "bib": {"title": "Heuristic voting as ordinal dominance strategies", "pub_year": "2019", "citation": "Proceedings of the AAAI Conference on Artificial Intelligence 33 (01), 2077-2084, 2019"}, "filled": false, "author_pub_id": "aorQUi0AAAAJ:R3hNpaxXUhUC", "num_citations": 5, "citedby_url": "https://scholar.google.com/scholar?oi=bibs&hl=en&cites=2045442106525663992", "cites_id": ["2045442106525663992"], "public_access": true}, {"container_type": "Publication", "source": "AUTHOR_PUBLICATION_ENTRY", "bib": {"title": "Local structure of 5 and 6-connected graphs", "pub_year": "2010", "citation": "Zapiski Nauchnykh Seminarov POMI 381, 88-96, 2010"}, "filled": false, "author_pub_id": "aorQUi0AAAAJ:zYLM7Y9cAGgC", "num_citations": 4, "citedby_url": "https://scholar.google.com/scholar?oi=bibs&hl=en&cites=14054428131225676536", "cites_id": ["14054428131225676536"], "public_access": null}, {"container_type": "Publication", "source": "AUTHOR_PUBLICATION_ENTRY", "bib": {"title": "Teams in online scheduling polls: Game-theoretic aspects", "pub_year": "2017", "citation": "Thirty-First AAAI Conference on Artificial Intelligence, 2017"}, "filled": false, "author_pub_id": "aorQUi0AAAAJ:IWHjjKOFINEC", "num_citations": 3, "citedby_url": "https://scholar.google.com/scholar?oi=bibs&hl=en&cites=6419477316359612765", "cites_id": ["6419477316359612765"], "public_access": true}, {"container_type": "Publication", "source": "AUTHOR_PUBLICATION_ENTRY", "bib": {"title": "Equilibria of plurality voting: Lazy and truth-biased voters", "pub_year": "2014", "citation": "arXiv preprint arXiv:1409.4132, 2014"}, "filled": false, "author_pub_id": "aorQUi0AAAAJ:qUcmZB5y_30C", "num_citations": 3, "citedby_url": "https://scholar.google.com/scholar?oi=bibs&hl=en&cites=15178781147384320237", "cites_id": ["15178781147384320237"], "public_access": null}, {"container_type": "Publication", "source": "AUTHOR_PUBLICATION_ENTRY", "bib": {"title": "On local structure of 9-and 10-connected graphs", "pub_year": "2012", "citation": "Journal of Mathematical Sciences 184 (5), 634-654, 2012"}, "filled": false, "author_pub_id": "aorQUi0AAAAJ:Y0pCki6q_DkC", "num_citations": 3, "citedby_url": "https://scholar.google.com/scholar?oi=bibs&hl=en&cites=5564124988163359249,2637693846559073555", "cites_id": ["5564124988163359249", "2637693846559073555"], "public_access": null}, {"container_type": "Publication", "source": "AUTHOR_PUBLICATION_ENTRY", "bib": {"title": "Local structure of 7 and 8-connected graphs", "pub_year": "2010", "citation": "Zapiski Nauchnykh Seminarov POMI 381, 97-111, 2010"}, "filled": false, "author_pub_id": "aorQUi0AAAAJ:9yKSN-GCB0IC", "num_citations": 3, "citedby_url": "https://scholar.google.com/scholar?oi=bibs&hl=en&cites=1234782718895577884", "cites_id": ["1234782718895577884"], "public_access": null}, {"container_type": "Publication", "source": "AUTHOR_PUBLICATION_ENTRY", "bib": {"title": "Reaching consensus under a deadline", "pub_year": "2021", "citation": "Autonomous Agents and Multi-Agent Systems 35 (1), 1-42, 2021"}, "filled": false, "author_pub_id": "aorQUi0AAAAJ:hMod-77fHWUC", "num_citations": 2, "citedby_url": "https://scholar.google.com/scholar?oi=bibs&hl=en&cites=12517639149133855248,1761168153717632440", "cites_id": ["12517639149133855248", "1761168153717632440"], "public_access": null}, {"container_type": "Publication", "source": "AUTHOR_PUBLICATION_ENTRY", "bib": {"title": "Faustian dynamics in Sarkar's social cycle", "pub_year": "2014", "citation": "ECAI 2014, 1071-1072, 2014"}, "filled": false, "author_pub_id": "aorQUi0AAAAJ:MXK_kJrjxJIC", "num_citations": 2, "citedby_url": "https://scholar.google.com/scholar?oi=bibs&hl=en&cites=17799928663649508713", "cites_id": ["17799928663649508713"], "public_access": null}, {"container_type": "Publication", "source": "AUTHOR_PUBLICATION_ENTRY", "bib": {"title": "About vertices of degree k of minimally and contraction critically k-connected graphs: upper bounds", "pub_year": "2011", "citation": "Zapiski Nauchnykh Seminarov POMI 391, 198-210, 2011"}, "filled": false, "author_pub_id": "aorQUi0AAAAJ:IjCSPb-OGe4C", "num_citations": 2, "citedby_url": "https://scholar.google.com/scholar?oi=bibs&hl=en&cites=10753354878359408164", "cites_id": ["10753354878359408164"], "public_access": null}, {"container_type": "Publication", "source": "AUTHOR_PUBLICATION_ENTRY", "bib": {"title": "RMIX: Risk-Sensitive Multi-Agent Reinforcement Learning", "pub_year": "2020", "citation": ""}, "filled": false, "author_pub_id": "aorQUi0AAAAJ:YFjsv_pBGBYC", "num_citations": 1, "citedby_url": "https://scholar.google.com/scholar?oi=bibs&hl=en&cites=861224197576803379", "cites_id": ["861224197576803379"], "public_access": null}, {"container_type": "Publication", "source": "AUTHOR_PUBLICATION_ENTRY", "bib": {"title": "Multiwinner candidacy games", "pub_year": "2020", "citation": "International Foundation for Autonomous Agents and Multiagent Systems, 2020"}, "filled": false, "author_pub_id": "aorQUi0AAAAJ:M3NEmzRMIkIC", "num_citations": 1, "citedby_url": "https://scholar.google.com/scholar?oi=bibs&hl=en&cites=1217636220158487776", "cites_id": ["1217636220158487776"], "public_access": true}, {"container_type": "Publication", "source": "AUTHOR_PUBLICATION_ENTRY", "bib": {"title": "On swap convexity of voting rules", "pub_year": "2020", "citation": "Proceedings of the AAAI Conference on Artificial Intelligence 34 (02), 1910-1917, 2020"}, "filled": false, "author_pub_id": "aorQUi0AAAAJ:k_IJM867U9cC", "num_citations": 1, "citedby_url": "https://scholar.google.com/scholar?oi=bibs&hl=en&cites=17803491970412125748", "cites_id": ["17803491970412125748"], "public_access": true}, {"container_type": "Publication", "source": "AUTHOR_PUBLICATION_ENTRY", "bib": {"title": "Local structure of 5-and 6-connected graphs.", "pub_year": "2011", "citation": "Journal of Mathematical Sciences 179 (5), 2011"}, "filled": false, "author_pub_id": "aorQUi0AAAAJ:M3ejUd6NZC8C", "num_citations": 1, "citedby_url": "https://scholar.google.com/scholar?oi=bibs&hl=en&cites=6548158862754193266", "cites_id": ["6548158862754193266"], "public_access": null}, {"container_type": "Publication", "source": "AUTHOR_PUBLICATION_ENTRY", "bib": {"title": "Local structure of 7-and 8-connected graphs.", "pub_year": "2011", "citation": "Journal of Mathematical Sciences 179 (5), 2011"}, "filled": false, "author_pub_id": "aorQUi0AAAAJ:qjMakFHDy7sC", "num_citations": 1, "citedby_url": "https://scholar.google.com/scholar?oi=bibs&hl=en&cites=6840736836367232927", "cites_id": ["6840736836367232927"], "public_access": null}, {"container_type": "Publication", "source": "AUTHOR_PUBLICATION_ENTRY", "bib": {"title": "RPM: Generalizable Behaviors for Multi-Agent Reinforcement Learning", "pub_year": "2022", "citation": "arXiv preprint arXiv:2210.09646, 2022"}, "filled": false, "author_pub_id": "aorQUi0AAAAJ:J_g5lzvAfSwC", "num_citations": 0, "citedby_url": null, "cites_id": null, "public_access": null}, {"container_type": "Publication", "source": "AUTHOR_PUBLICATION_ENTRY", "bib": {"title": "Off-Beat Multi-Agent Reinforcement Learning", "pub_year": "2022", "citation": "arXiv preprint arXiv:2205.13718, 2022"}, "filled": false, "author_pub_id": "aorQUi0AAAAJ:ns9cj8rnVeAC", "num_citations": 0, "citedby_url": null, "cites_id": null, "public_access": null}, {"container_type": "Publication", "source": "AUTHOR_PUBLICATION_ENTRY", "bib": {"title": "Hotelling-Downs Equilibria: Moving Beyond Plurality Variants", "pub_year": "2022", "citation": "International Conference on Group Decision and Negotiation, 3-16, 2022"}, "filled": false, "author_pub_id": "aorQUi0AAAAJ:O3NaXMp0MMsC", "num_citations": 0, "citedby_url": null, "cites_id": null, "public_access": null}, {"container_type": "Publication", "source": "AUTHOR_PUBLICATION_ENTRY", "bib": {"title": "Stategic Candidacy with Keen Candidates", "pub_year": "2019", "citation": ""}, "filled": false, "author_pub_id": "aorQUi0AAAAJ:iH-uZ7U-co4C", "num_citations": 0, "citedby_url": null, "cites_id": null, "public_access": true}, {"container_type": "Publication", "source": "AUTHOR_PUBLICATION_ENTRY", "bib": {"title": "These Polar Twins: Opinion Dynamics of Intervals", "pub_year": "2019", "citation": ""}, "filled": false, "author_pub_id": "aorQUi0AAAAJ:bEWYMUwI8FkC", "num_citations": 0, "citedby_url": null, "cites_id": null, "public_access": null}, {"container_type": "Publication", "source": "AUTHOR_PUBLICATION_ENTRY", "bib": {"title": "IJCAI INTERNATIONAL JOINT CONFERENCE ON ARTIFICIAL INTELLIGENCE", "pub_year": "2015", "citation": "Convergence 610, 616, 2015"}, "filled": false, "author_pub_id": "aorQUi0AAAAJ:blknAaTinKkC", "num_citations": 0, "citedby_url": null, "cites_id": null, "public_access": null}, {"container_type": "Publication", "source": "AUTHOR_PUBLICATION_ENTRY", "bib": {"title": "Essays on the Complexity of Voting Manipulation", "pub_year": "2012", "citation": "Nanyang Technological University, 2012"}, "filled": false, "author_pub_id": "aorQUi0AAAAJ:ZeXyd9-uunAC", "num_citations": 0, "citedby_url": null, "cites_id": null, "public_access": null}, {"container_type": "Publication", "source": "AUTHOR_PUBLICATION_ENTRY", "bib": {"title": "On vertices of degree k of minimal and contraction critical k-connected graphs: upper bounds.", "pub_year": "2012", "citation": "Journal of Mathematical Sciences 184 (5), 2012"}, "filled": false, "author_pub_id": "aorQUi0AAAAJ:W7OEmFMy1HYC", "num_citations": 0, "citedby_url": null, "cites_id": null, "public_access": null}, {"container_type": "Publication", "source": "AUTHOR_PUBLICATION_ENTRY", "bib": {"title": "On the chromatic uniqueness of -homeomorphs with girth 7", "pub_year": "2010", "citation": "arXiv preprint arXiv:1010.4146, 2010"}, "filled": false, "author_pub_id": "aorQUi0AAAAJ:YsMSGLbcyi4C", "num_citations": 0, "citedby_url": null, "cites_id": null, "public_access": null}, {"container_type": "Publication", "source": "AUTHOR_PUBLICATION_ENTRY", "bib": {"title": "Cliques in k-connected graphs", "pub_year": "2007", "citation": "Journal of Mathematical Sciences 145 (3), 4975-4980, 2007"}, "filled": false, "author_pub_id": "aorQUi0AAAAJ:UeHWp8X0CEIC", "num_citations": 0, "citedby_url": null, "cites_id": null, "public_access": null}, {"container_type": "Publication", "source": "AUTHOR_PUBLICATION_ENTRY", "bib": {"title": "Neither here nor there", "pub_year": null, "citation": ""}, "filled": false, "author_pub_id": "aorQUi0AAAAJ:GnPB-g6toBAC", "num_citations": 0, "citedby_url": null, "cites_id": null, "public_access": null}, {"container_type": "Publication", "source": "AUTHOR_PUBLICATION_ENTRY", "bib": {"title": "Truth-Bias Complexity in the Veto Voting Rule", "pub_year": null, "citation": ""}, "filled": false, "author_pub_id": "aorQUi0AAAAJ:ULOm3_A8WrAC", "num_citations": 0, "citedby_url": null, "cites_id": null, "public_access": null}], "public_access": {"available": 18, "not_available": 0}}