{"container_type": "Author", "filled": ["basics", "indices", "counts", "coauthors", "publications", "public_access"], "source": "SEARCH_AUTHOR_SNIPPETS", "scholar_id": "am2ohp0AAAAJ", "url_picture": "https://scholar.google.com/citations?view_op=medium_photo&user=am2ohp0AAAAJ", "name": "Alexander L\u00f6ser", "affiliation": "Professor for Data Science and Text-based Information Systems", "email_domain": "@bht-berlin.de", "interests": ["Clinical Text Mining", "Machine Reading", "Language Technology"], "citedby": 2430, "organization": null, "homepage": "http://www.datexis.com/", "citedby5y": 926, "hindex": 21, "hindex5y": 15, "i10index": 42, "i10index5y": 20, "cites_per_year": {"2003": 38, "2004": 109, "2005": 123, "2006": 142, "2007": 111, "2008": 116, "2009": 117, "2010": 102, "2011": 118, "2012": 81, "2013": 97, "2014": 121, "2015": 84, "2016": 104, "2017": 82, "2018": 100, "2019": 139, "2020": 194, "2021": 225, "2022": 182}, "coauthors": [{"container_type": "Author", "filled": [], "scholar_id": "2rAsiHAAAAAJ", "source": "CO_AUTHORS_LIST", "name": "Felix Gers", "affiliation": "Professor of Computer Science, Berliner Hochschule f\u00fcr Technik (BHT)"}, {"container_type": "Author", "filled": [], "scholar_id": "LC62bdYAAAAJ", "source": "CO_AUTHORS_LIST", "name": "Wolfgang Nejdl", "affiliation": "Professor of Computer Science, Leibniz Universit\u00e4t Hannover, L3S Research Center \u2026"}, {"container_type": "Author", "filled": [], "scholar_id": "3V75H5QAAAAJ", "source": "CO_AUTHORS_LIST", "name": "Betty van Aken", "affiliation": "Research Assistant, Berliner Hochschule f\u00fcr Technik (BHT)"}, {"container_type": "Author", "filled": [], "scholar_id": "WwPL3-sAAAAJ", "source": "CO_AUTHORS_LIST", "name": "Sebastian Arnold", "affiliation": "Research Assistant, Beuth University of Applied Sciences Berlin"}, {"container_type": "Author", "filled": [], "scholar_id": "l_ySP6UAAAAJ", "source": "CO_AUTHORS_LIST", "name": "Martin Wolpers", "affiliation": "Fraunhofer Institute for Applied Information Technology"}, {"container_type": "Author", "filled": [], "scholar_id": "0cQoDxcAAAAJ", "source": "CO_AUTHORS_LIST", "name": "Christoph Tempich", "affiliation": "v. Rundstedt & Partner GmbH"}, {"container_type": "Author", "filled": [], "scholar_id": "el2k_oIAAAAJ", "source": "CO_AUTHORS_LIST", "name": "Volker Markl", "affiliation": "Technische Universit\u00e4t Berlin"}, {"container_type": "Author", "filled": [], "scholar_id": "QvpcUn8AAAAJ", "source": "CO_AUTHORS_LIST", "name": "Steffen Staab", "affiliation": "WAIS, University of Southampton, UK & Analytic Computing, Universit\u00e4t Stuttgart, DE &"}, {"container_type": "Author", "filled": [], "scholar_id": "j4SwxYgAAAAJ", "source": "CO_AUTHORS_LIST", "name": "Rudolf Schneider", "affiliation": "Research Assistant"}, {"container_type": "Author", "filled": [], "scholar_id": "3GW9-V8AAAAJ", "source": "CO_AUTHORS_LIST", "name": "Torsten Kilias", "affiliation": "EXASOL Big Data Technologies GmbH"}, {"container_type": "Author", "filled": [], "scholar_id": "adKmg3IAAAAJ", "source": "CO_AUTHORS_LIST", "name": "Alan Akbik", "affiliation": "Humboldt-Universit\u00e4t zu Berlin"}, {"container_type": "Author", "filled": [], "scholar_id": "ABYevP4AAAAJ", "source": "CO_AUTHORS_LIST", "name": "Gottfried Vossen", "affiliation": "Professor of Computer Science, University of Muenster, Germany"}, {"container_type": "Author", "filled": [], "scholar_id": "nNsC6rMAAAAJ", "source": "CO_AUTHORS_LIST", "name": "Mario Schlosser", "affiliation": "Stanford University, Harvard Business School"}, {"container_type": "Author", "filled": [], "scholar_id": "9TZJQSAAAAAJ", "source": "CO_AUTHORS_LIST", "name": "Christoph Boden", "affiliation": "Research Associate, TU Berlin"}, {"container_type": "Author", "filled": [], "scholar_id": "_JnLJDgAAAAJ", "source": "CO_AUTHORS_LIST", "name": "Tom Oberhauser", "affiliation": "Beuth University of Applied Sciences Berlin"}, {"container_type": "Author", "filled": [], "scholar_id": "pyJxSNUAAAAJ", "source": "CO_AUTHORS_LIST", "name": "Benjamin Winter", "affiliation": "Beuth University of Applied Sciences"}, {"container_type": "Author", "filled": [], "scholar_id": "Pqf21y0AAAAJ", "source": "CO_AUTHORS_LIST", "name": "Felix Naumann", "affiliation": "Hasso Plattner Institute, University of Potsdam"}, {"container_type": "Author", "filled": [], "scholar_id": "OL0cR8QAAAAJ", "source": "CO_AUTHORS_LIST", "name": "Klemens Budde", "affiliation": "Charit\u00e9 Universit\u00e4tsmedizin Berlin"}, {"container_type": "Author", "filled": [], "scholar_id": "pA7lT78AAAAJ", "source": "CO_AUTHORS_LIST", "name": "Florian Stahl", "affiliation": "Research Assistant, ERCIS"}, {"container_type": "Author", "filled": [], "scholar_id": "DlAra1sAAAAJ", "source": "CO_AUTHORS_LIST", "name": "Holmer Hemsen", "affiliation": "Senior Researcher, DFKI"}, {"container_type": "Author", "filled": [], "scholar_id": "6BZTybkAAAAJ", "source": "CO_AUTHORS_LIST", "name": "Ralf Krestel", "affiliation": "ZBW - Leibniz Information Centre for Economics & Kiel University"}, {"container_type": "Author", "filled": [], "scholar_id": "sBjOp_YAAAAJ", "source": "CO_AUTHORS_LIST", "name": "Julian Risch", "affiliation": "deepset | PhD from Hasso Plattner Institute, University of Potsdam"}, {"container_type": "Author", "filled": [], "scholar_id": "Kr6jppsAAAAJ", "source": "CO_AUTHORS_LIST", "name": "Martin Kersten", "affiliation": "Research Fellow, CWI, Amsterdam"}, {"container_type": "Author", "filled": [], "scholar_id": "_9oHmkAAAAAJ", "source": "CO_AUTHORS_LIST", "name": "Larysa Visengeriyeva", "affiliation": "Beuth University of Applied Science"}, {"container_type": "Author", "filled": [], "scholar_id": "fI5mXFgAAAAJ", "source": "CO_AUTHORS_LIST", "name": "Huaiyu Zhu", "affiliation": "IBM Research - Almaden"}, {"container_type": "Author", "filled": [], "scholar_id": "xNpDx0gAAAAJ", "source": "CO_AUTHORS_LIST", "name": "Manuel Mayrdorfer", "affiliation": "Charit\u00e9 Universit\u00e4tsmedizin Berlin"}, {"container_type": "Author", "filled": [], "scholar_id": "cKUFV0sAAAAJ", "source": "CO_AUTHORS_LIST", "name": "Michael Schermann", "affiliation": "Santa Clara University"}, {"container_type": "Author", "filled": [], "scholar_id": "zwax5qkAAAAJ", "source": "CO_AUTHORS_LIST", "name": "Helmut Krcmar", "affiliation": "Professor of Information Systems, Technische Universit\u00e4t M\u00fcnchen"}, {"container_type": "Author", "filled": [], "scholar_id": "NKJeIJkAAAAJ", "source": "CO_AUTHORS_LIST", "name": "Fabian Hueske", "affiliation": "Senior Software Engineer @ Snowflake"}, {"container_type": "Author", "filled": [], "scholar_id": "1GYUnQoAAAAJ", "source": "CO_AUTHORS_LIST", "name": "Alexandre Passant", "affiliation": "Founder at seevl.fm / mdg.io ; Ex Research Fellow / Unit Lead at DERI, NUI Galway, IE"}, {"container_type": "Author", "filled": [], "scholar_id": "oI0X4CQAAAAJ", "source": "CO_AUTHORS_LIST", "name": "Peter Mika", "affiliation": "Yahoo! Research"}, {"container_type": "Author", "filled": [], "scholar_id": "ppmWnkQAAAAJ", "source": "CO_AUTHORS_LIST", "name": "Ian Mulvany", "affiliation": ""}, {"container_type": "Author", "filled": [], "scholar_id": "Wi4cDJIAAAAJ", "source": "CO_AUTHORS_LIST", "name": "Harith Alani", "affiliation": "Professor at the Knowledge Media institute, Open University, UK"}, {"container_type": "Author", "filled": [], "scholar_id": "f9iP-80AAAAJ", "source": "CO_AUTHORS_LIST", "name": "Christian Bauckhage", "affiliation": "Prof. of Computer Science, University of Bonn, Fraunhofer IAIS"}, {"container_type": "Author", "filled": [], "scholar_id": "qOv3StkAAAAJ", "source": "CO_AUTHORS_LIST", "name": "Ciro Cattuto", "affiliation": "ISI Foundation and University of Torino"}, {"container_type": "Author", "filled": [], "scholar_id": "VQFR1sgAAAAJ", "source": "CO_AUTHORS_LIST", "name": "Ying Zhang", "affiliation": "MonetDB Solutions"}, {"container_type": "Author", "filled": [], "scholar_id": "NpccCXwAAAAJ", "source": "CO_AUTHORS_LIST", "name": "Philippe Cudre-Mauroux", "affiliation": "Full Professor (Computer Science), U. of Fribourg\u2013Switzerland"}, {"container_type": "Author", "filled": [], "scholar_id": "Vtd-PgEAAAAJ", "source": "CO_AUTHORS_LIST", "name": "Wolf-Tilo Balke", "affiliation": "Technische Universit\u00e4t Braunschweig"}, {"container_type": "Author", "filled": [], "scholar_id": "4gP-dEIAAAAJ", "source": "CO_AUTHORS_LIST", "name": "Periklis Andritsos", "affiliation": "Faculty of Information"}, {"container_type": "Author", "filled": [], "scholar_id": "TABb2iQAAAAJ", "source": "CO_AUTHORS_LIST", "name": "Alexander Schill", "affiliation": "TU Dresden"}, {"container_type": "Author", "filled": [], "scholar_id": "crhkrNcAAAAJ", "source": "CO_AUTHORS_LIST", "name": "Alessandro Checco", "affiliation": "Computer Science Department - University of Rome La Sapienza"}, {"container_type": "Author", "filled": [], "scholar_id": "MotmYWgAAAAJ", "source": "CO_AUTHORS_LIST", "name": "Amy Siu", "affiliation": "Beuth University of Applied Sciences"}, {"container_type": "Author", "filled": [], "scholar_id": "QUKgKMUAAAAJ", "source": "CO_AUTHORS_LIST", "name": "Matthias Gottlieb", "affiliation": "Technische Universit\u00e4t M\u00fcnchen"}, {"container_type": "Author", "filled": [], "scholar_id": "MzyKw-DOYF4C", "source": "CO_AUTHORS_LIST", "name": "Roland Roller", "affiliation": "German Research Center for Artificial Intelligence (DFKI)"}, {"container_type": "Author", "filled": [], "scholar_id": "XAW1rCcAAAAJ", "source": "CO_AUTHORS_LIST", "name": "Hans Uszkoreit", "affiliation": "Giance, DFKI, Saarland University"}, {"container_type": "Author", "filled": [], "scholar_id": "7Q4XxHcAAAAJ", "source": "CO_AUTHORS_LIST", "name": "Kai Sachs", "affiliation": "SaltPay"}, {"container_type": "Author", "filled": [], "scholar_id": "MVUgMkUAAAAJ", "source": "CO_AUTHORS_LIST", "name": "Mourad Khayati", "affiliation": "Senior Researcher, University of Fribourg"}, {"container_type": "Author", "filled": [], "scholar_id": "RWXHLa8AAAAJ", "source": "CO_AUTHORS_LIST", "name": "Ines Arous", "affiliation": "University of Fribourg-Switzerland"}, {"container_type": "Author", "filled": [], "scholar_id": "PCAiILsAAAAJ", "source": "CO_AUTHORS_LIST", "name": "Gianluca Demartini", "affiliation": "Associate Professor at the University of Queensland"}, {"container_type": "Author", "filled": [], "scholar_id": "mLp9H4oAAAAJ", "source": "CO_AUTHORS_LIST", "name": "Matthias Dantone", "affiliation": "ETH Zuerich - Fashwell"}, {"container_type": "Author", "filled": [], "scholar_id": "aUU3IuUAAAAJ", "source": "CO_AUTHORS_LIST", "name": "Jens Graupmann", "affiliation": "EXASOL AG (until 2006: Max Planck Institute for Informatics)"}, {"container_type": "Author", "filled": [], "scholar_id": "bOWp9HwAAAAJ", "source": "CO_AUTHORS_LIST", "name": "Konstantina Lazaridou", "affiliation": "University of Potsdam, Beuth University in Berlin"}, {"container_type": "Author", "filled": [], "scholar_id": "1dh-y6QAAAAJ", "source": "CO_AUTHORS_LIST", "name": "Dr Maria R. Mestre", "affiliation": "PhD student, Cambridge"}, {"container_type": "Author", "filled": [], "scholar_id": "INQwsQkAAAAJ", "source": "CO_AUTHORS_LIST", "name": "Christian Bizer", "affiliation": "Professor of Information Systems, University of Mannheim, Germany"}, {"container_type": "Author", "filled": [], "scholar_id": "brRghoAAAAAJ", "source": "CO_AUTHORS_LIST", "name": "Wolf Siberski", "affiliation": "SYNAOS GmbH"}, {"container_type": "Author", "filled": [], "scholar_id": "m_bfdYwAAAAJ", "source": "CO_AUTHORS_LIST", "name": "Feiyu Xu", "affiliation": "Senior Vice President, Global Head of Artificial Intelligence, SAP"}], "publications": [{"container_type": "Publication", "source": "AUTHOR_PUBLICATION_ENTRY", "bib": {"title": "Super-peer-based routing and clustering strategies for RDF-based peer-to-peer networks", "pub_year": "2003", "citation": "Proceedings of the 12th international conference on World Wide Web, 536-543, 2003"}, "filled": false, "author_pub_id": "am2ohp0AAAAJ:u5HHmVD_uO8C", "num_citations": 547, "citedby_url": "https://scholar.google.com/scholar?oi=bibs&hl=en&cites=10908194397599434488", "cites_id": ["10908194397599434488"], "public_access": null}, {"container_type": "Publication", "source": "AUTHOR_PUBLICATION_ENTRY", "bib": {"title": "Semantic overlay clusters within super-peer networks", "pub_year": "2003", "citation": "International Workshop on Databases, Information Systems, and Peer-to-Peer \u2026, 2003"}, "filled": false, "author_pub_id": "am2ohp0AAAAJ:u-x6o8ySG0sC", "num_citations": 193, "citedby_url": "https://scholar.google.com/scholar?oi=bibs&hl=en&cites=2239012690957751999", "cites_id": ["2239012690957751999"], "public_access": null}, {"container_type": "Publication", "source": "AUTHOR_PUBLICATION_ENTRY", "bib": {"title": "Challenges for toxic comment classification: An in-depth error analysis", "pub_year": "2018", "citation": "arXiv preprint arXiv:1809.07572, 2018"}, "filled": false, "author_pub_id": "am2ohp0AAAAJ:4fKUyHm3Qg0C", "num_citations": 178, "citedby_url": "https://scholar.google.com/scholar?oi=bibs&hl=en&cites=11117686808335778617", "cites_id": ["11117686808335778617"], "public_access": null}, {"container_type": "Publication", "source": "AUTHOR_PUBLICATION_ENTRY", "bib": {"title": "Kraken: N-ary facts in open information extraction", "pub_year": "2012", "citation": "Proceedings of the Joint Workshop on Automatic Knowledge Base Construction \u2026, 2012"}, "filled": false, "author_pub_id": "am2ohp0AAAAJ:7PzlFSSx8tAC", "num_citations": 132, "citedby_url": "https://scholar.google.com/scholar?oi=bibs&hl=en&cites=14279309313429779203", "cites_id": ["14279309313429779203"], "public_access": null}, {"container_type": "Publication", "source": "AUTHOR_PUBLICATION_ENTRY", "bib": {"title": "Pricing approaches for data markets", "pub_year": "2012", "citation": "International workshop on business intelligence for the real-time enterprise \u2026, 2012"}, "filled": false, "author_pub_id": "am2ohp0AAAAJ:9ZlFYXVOiuMC", "num_citations": 119, "citedby_url": "https://scholar.google.com/scholar?oi=bibs&hl=en&cites=16333867389479262794", "cites_id": ["16333867389479262794"], "public_access": null}, {"container_type": "Publication", "source": "AUTHOR_PUBLICATION_ENTRY", "bib": {"title": "How does bert answer questions? a layer-wise analysis of transformer representations", "pub_year": "2019", "citation": "Proceedings of the 28th ACM International Conference on Information and \u2026, 2019"}, "filled": false, "author_pub_id": "am2ohp0AAAAJ:bnK-pcrLprsC", "num_citations": 110, "citedby_url": "https://scholar.google.com/scholar?oi=bibs&hl=en&cites=5807766067586263378", "cites_id": ["5807766067586263378"], "public_access": true}, {"container_type": "Publication", "source": "AUTHOR_PUBLICATION_ENTRY", "bib": {"title": "Graph based re-composition of document fragments for name entity recognition under exploitation of enterprise databases", "pub_year": "2012", "citation": "US Patent 8,229,883, 2012"}, "filled": false, "author_pub_id": "am2ohp0AAAAJ:hC7cP41nSMkC", "num_citations": 96, "citedby_url": "https://scholar.google.com/scholar?oi=bibs&hl=en&cites=17167721199165858924", "cites_id": ["17167721199165858924"], "public_access": null}, {"container_type": "Publication", "source": "AUTHOR_PUBLICATION_ENTRY", "bib": {"title": "Information integration in schema-based peer-to-peer networks", "pub_year": "2003", "citation": "International Conference on Advanced Information Systems Engineering, 258-272, 2003"}, "filled": false, "author_pub_id": "am2ohp0AAAAJ:d1gkVwhDpl0C", "num_citations": 95, "citedby_url": "https://scholar.google.com/scholar?oi=bibs&hl=en&cites=13699704621082207916", "cites_id": ["13699704621082207916"], "public_access": null}, {"container_type": "Publication", "source": "AUTHOR_PUBLICATION_ENTRY", "bib": {"title": "Semantic social overlay networks", "pub_year": "2007", "citation": "IEEE Journal on selected areas in communications 25 (1), 5-14, 2007"}, "filled": false, "author_pub_id": "am2ohp0AAAAJ:R3hNpaxXUhUC", "num_citations": 67, "citedby_url": "https://scholar.google.com/scholar?oi=bibs&hl=en&cites=6415882867056414169,16349820338194806371", "cites_id": ["6415882867056414169", "16349820338194806371"], "public_access": true}, {"container_type": "Publication", "source": "AUTHOR_PUBLICATION_ENTRY", "bib": {"title": "Situational business intelligence", "pub_year": "2008", "citation": "International Workshop on Business Intelligence for the Real-Time Enterprise \u2026, 2008"}, "filled": false, "author_pub_id": "am2ohp0AAAAJ:Y0pCki6q_DkC", "num_citations": 65, "citedby_url": "https://scholar.google.com/scholar?oi=bibs&hl=en&cites=17590876805507511740", "cites_id": ["17590876805507511740"], "public_access": null}, {"container_type": "Publication", "source": "AUTHOR_PUBLICATION_ENTRY", "bib": {"title": "Automatically generating regular expressions for relaxed matching of text patterns", "pub_year": "2013", "citation": "US Patent 8,484,238, 2013"}, "filled": false, "author_pub_id": "am2ohp0AAAAJ:qxL8FJ1GzNcC", "num_citations": 54, "citedby_url": "https://scholar.google.com/scholar?oi=bibs&hl=en&cites=8395254112845098068", "cites_id": ["8395254112845098068"], "public_access": null}, {"container_type": "Publication", "source": "AUTHOR_PUBLICATION_ENTRY", "bib": {"title": "Navigating the intranet with high precision", "pub_year": "2007", "citation": "Proceedings of the 16th international conference on World Wide Web, 491-500, 2007"}, "filled": false, "author_pub_id": "am2ohp0AAAAJ:IjCSPb-OGe4C", "num_citations": 47, "citedby_url": "https://scholar.google.com/scholar?oi=bibs&hl=en&cites=3182353126795585281", "cites_id": ["3182353126795585281"], "public_access": null}, {"container_type": "Publication", "source": "AUTHOR_PUBLICATION_ENTRY", "bib": {"title": "Method for automatically generating regular expressions for relaxed matching of text patterns", "pub_year": "2009", "citation": "US Patent App. 11/850,987, 2009"}, "filled": false, "author_pub_id": "am2ohp0AAAAJ:kNdYIx-mwKoC", "num_citations": 46, "citedby_url": "https://scholar.google.com/scholar?oi=bibs&hl=en&cites=17270156840219691255", "cites_id": ["17270156840219691255"], "public_access": null}, {"container_type": "Publication", "source": "AUTHOR_PUBLICATION_ENTRY", "bib": {"title": "SECTOR: A neural model for coherent topic segmentation and classification", "pub_year": "2019", "citation": "Transactions of the Association for Computational Linguistics 7, 169-184, 2019"}, "filled": false, "author_pub_id": "am2ohp0AAAAJ:kRWSkSYxWN8C", "num_citations": 43, "citedby_url": "https://scholar.google.com/scholar?oi=bibs&hl=en&cites=17247579659932816540", "cites_id": ["17247579659932816540"], "public_access": true}, {"container_type": "Publication", "source": "AUTHOR_PUBLICATION_ENTRY", "bib": {"title": "Unsupervised discovery of relations and discriminative extraction patterns", "pub_year": "2012", "citation": "Proceedings of COLING 2012, 17-32, 2012"}, "filled": false, "author_pub_id": "am2ohp0AAAAJ:hFOr9nPyWt4C", "num_citations": 40, "citedby_url": "https://scholar.google.com/scholar?oi=bibs&hl=en&cites=11269233327981648427", "cites_id": ["11269233327981648427"], "public_access": null}, {"container_type": "Publication", "source": "AUTHOR_PUBLICATION_ENTRY", "bib": {"title": "Searching dynamic communities with personal indexes", "pub_year": "2005", "citation": "International Semantic Web Conference, 491-505, 2005"}, "filled": false, "author_pub_id": "am2ohp0AAAAJ:qjMakFHDy7sC", "num_citations": 34, "citedby_url": "https://scholar.google.com/scholar?oi=bibs&hl=en&cites=18318063629657624940", "cites_id": ["18318063629657624940"], "public_access": null}, {"container_type": "Publication", "source": "AUTHOR_PUBLICATION_ENTRY", "bib": {"title": "Efficient data store discovery in a scientific P2P network", "pub_year": "2003", "citation": "Proc. of the WS on Semantic Web Technologies for Searching and Retrieving \u2026, 2003"}, "filled": false, "author_pub_id": "am2ohp0AAAAJ:2osOgNQ5qMEC", "num_citations": 34, "citedby_url": "https://scholar.google.com/scholar?oi=bibs&hl=en&cites=9921430015680681249", "cites_id": ["9921430015680681249"], "public_access": null}, {"container_type": "Publication", "source": "AUTHOR_PUBLICATION_ENTRY", "bib": {"title": "Analysing errors of open information extraction systems", "pub_year": "2017", "citation": "arXiv preprint arXiv:1707.07499, 2017"}, "filled": false, "author_pub_id": "am2ohp0AAAAJ:uWQEDVKXjbEC", "num_citations": 33, "citedby_url": "https://scholar.google.com/scholar?oi=bibs&hl=en&cites=9668014607755483139", "cites_id": ["9668014607755483139"], "public_access": null}, {"container_type": "Publication", "source": "AUTHOR_PUBLICATION_ENTRY", "bib": {"title": "Semantic methods for p2p query routing", "pub_year": "2005", "citation": "German Conference on Multiagent System Technologies, 15-26, 2005"}, "filled": false, "author_pub_id": "am2ohp0AAAAJ:UeHWp8X0CEIC", "num_citations": 30, "citedby_url": "https://scholar.google.com/scholar?oi=bibs&hl=en&cites=15350090259521441144", "cites_id": ["15350090259521441144"], "public_access": null}, {"container_type": "Publication", "source": "AUTHOR_PUBLICATION_ENTRY", "bib": {"title": "Temporal constraints for rule-based event processing", "pub_year": "2007", "citation": "Proceedings of the ACM first Ph. D. workshop in CIKM, 93-100, 2007"}, "filled": false, "author_pub_id": "am2ohp0AAAAJ:eQOLeE2rZwMC", "num_citations": 25, "citedby_url": "https://scholar.google.com/scholar?oi=bibs&hl=en&cites=6445003424052232129", "cites_id": ["6445003424052232129"], "public_access": null}, {"container_type": "Publication", "source": "AUTHOR_PUBLICATION_ENTRY", "bib": {"title": "Near-duplicate detection for web-forums", "pub_year": "2009", "citation": "Proceedings of the 2009 International Database Engineering & Applications \u2026, 2009"}, "filled": false, "author_pub_id": "am2ohp0AAAAJ:YsMSGLbcyi4C", "num_citations": 21, "citedby_url": "https://scholar.google.com/scholar?oi=bibs&hl=en&cites=3328681113493794877", "cites_id": ["3328681113493794877"], "public_access": null}, {"container_type": "Publication", "source": "AUTHOR_PUBLICATION_ENTRY", "bib": {"title": "Community based ranking in peer-to-peer networks", "pub_year": "2005", "citation": "OTM Confederated International Conferences\" On the Move to Meaningful \u2026, 2005"}, "filled": false, "author_pub_id": "am2ohp0AAAAJ:Tyk-4Ss8FVUC", "num_citations": 20, "citedby_url": "https://scholar.google.com/scholar?oi=bibs&hl=en&cites=12861062586211125540", "cites_id": ["12861062586211125540"], "public_access": null}, {"container_type": "Publication", "source": "AUTHOR_PUBLICATION_ENTRY", "bib": {"title": "Clinical outcome prediction from admission notes using self-supervised knowledge integration", "pub_year": "2021", "citation": "arXiv preprint arXiv:2102.04110, 2021"}, "filled": false, "author_pub_id": "am2ohp0AAAAJ:tkaPQYYpVKoC", "num_citations": 19, "citedby_url": "https://scholar.google.com/scholar?oi=bibs&hl=en&cites=911329985586998527", "cites_id": ["911329985586998527"], "public_access": null}, {"container_type": "Publication", "source": "AUTHOR_PUBLICATION_ENTRY", "bib": {"title": "Visbert: Hidden-state visualizations for transformers", "pub_year": "2020", "citation": "Companion Proceedings of the Web Conference 2020, 207-211, 2020"}, "filled": false, "author_pub_id": "am2ohp0AAAAJ:WA5NYHcadZ8C", "num_citations": 19, "citedby_url": "https://scholar.google.com/scholar?oi=bibs&hl=en&cites=17357220731793648114", "cites_id": ["17357220731793648114"], "public_access": true}, {"container_type": "Publication", "source": "AUTHOR_PUBLICATION_ENTRY", "bib": {"title": "Preismodelle f\u00fcr datenmarktpl\u00e4tze", "pub_year": "2015", "citation": "Informatik-Spektrum 38 (2), 133-141, 2015"}, "filled": false, "author_pub_id": "am2ohp0AAAAJ:JV2RwH3_ST0C", "num_citations": 19, "citedby_url": "https://scholar.google.com/scholar?oi=bibs&hl=en&cites=2631688455134317063", "cites_id": ["2631688455134317063"], "public_access": null}, {"container_type": "Publication", "source": "AUTHOR_PUBLICATION_ENTRY", "bib": {"title": "Systems and methods for modular information extraction", "pub_year": "2011", "citation": "US Patent 7,987,416, 2011"}, "filled": false, "author_pub_id": "am2ohp0AAAAJ:ZeXyd9-uunAC", "num_citations": 19, "citedby_url": "https://scholar.google.com/scholar?oi=bibs&hl=en&cites=14609539173744426666", "cites_id": ["14609539173744426666"], "public_access": null}, {"container_type": "Publication", "source": "AUTHOR_PUBLICATION_ENTRY", "bib": {"title": "On Ranking Peers in Semantic Overlay Networks.", "pub_year": "2005", "citation": "Wissensmanagement, 209-216, 2005"}, "filled": false, "author_pub_id": "am2ohp0AAAAJ:zYLM7Y9cAGgC", "num_citations": 19, "citedby_url": "https://scholar.google.com/scholar?oi=bibs&hl=en&cites=9004405915609223831", "cites_id": ["9004405915609223831"], "public_access": null}, {"container_type": "Publication", "source": "AUTHOR_PUBLICATION_ENTRY", "bib": {"title": "Tasty: Interactive entity linking as-you-type", "pub_year": "2016", "citation": "Proceedings of COLING 2016, the 26th International Conference on \u2026, 2016"}, "filled": false, "author_pub_id": "am2ohp0AAAAJ:UxriW0iASnsC", "num_citations": 17, "citedby_url": "https://scholar.google.com/scholar?oi=bibs&hl=en&cites=6872061939168573751", "cites_id": ["6872061939168573751"], "public_access": null}, {"container_type": "Publication", "source": "AUTHOR_PUBLICATION_ENTRY", "bib": {"title": "Innovationspotenzialanalyse f\u00fcr die neuen Technologien f\u00fcr das Verwalten und Analysieren von gro\u00dfen Datenmengen (Big Data Management)", "pub_year": "2013", "citation": ""}, "filled": false, "author_pub_id": "am2ohp0AAAAJ:J_g5lzvAfSwC", "num_citations": 17, "citedby_url": "https://scholar.google.com/scholar?oi=bibs&hl=en&cites=16534230424076845662", "cites_id": ["16534230424076845662"], "public_access": null}, {"container_type": "Publication", "source": "AUTHOR_PUBLICATION_ENTRY", "bib": {"title": "Idel: In-database entity linking with neural embeddings", "pub_year": "2018", "citation": "arXiv preprint arXiv:1803.04884, 2018"}, "filled": false, "author_pub_id": "am2ohp0AAAAJ:WbkHhVStYXYC", "num_citations": 14, "citedby_url": "https://scholar.google.com/scholar?oi=bibs&hl=en&cites=3587274782147063662", "cites_id": ["3587274782147063662"], "public_access": null}, {"container_type": "Publication", "source": "AUTHOR_PUBLICATION_ENTRY", "bib": {"title": "Mining for social serendipity", "pub_year": "2008", "citation": ""}, "filled": false, "author_pub_id": "am2ohp0AAAAJ:ufrVoPGSRksC", "num_citations": 14, "citedby_url": "https://scholar.google.com/scholar?oi=bibs&hl=en&cites=7137034983861629550", "cites_id": ["7137034983861629550"], "public_access": null}, {"container_type": "Publication", "source": "AUTHOR_PUBLICATION_ENTRY", "bib": {"title": "A didactic model, definition of learning objects and selection of metadata for an online curriculum", "pub_year": "2002", "citation": "Proceedings of the International Workshop of Interactive Computer Aided \u2026, 2002"}, "filled": false, "author_pub_id": "am2ohp0AAAAJ:W7OEmFMy1HYC", "num_citations": 14, "citedby_url": "https://scholar.google.com/scholar?oi=bibs&hl=en&cites=5305074453493717054", "cites_id": ["5305074453493717054"], "public_access": null}, {"container_type": "Publication", "source": "AUTHOR_PUBLICATION_ENTRY", "bib": {"title": "The goolap fact retrieval framework", "pub_year": "2011", "citation": "European Business Intelligence Summer School, 84-97, 2011"}, "filled": false, "author_pub_id": "am2ohp0AAAAJ:Zph67rFs4hoC", "num_citations": 13, "citedby_url": "https://scholar.google.com/scholar?oi=bibs&hl=en&cites=13856289068431497272", "cites_id": ["13856289068431497272"], "public_access": null}, {"container_type": "Publication", "source": "AUTHOR_PUBLICATION_ENTRY", "bib": {"title": "Effective selectional restrictions for unsupervised relation extraction", "pub_year": "2013", "citation": "Proceedings of the Sixth International Joint Conference on Natural Language \u2026, 2013"}, "filled": false, "author_pub_id": "am2ohp0AAAAJ:isC4tDSrTZIC", "num_citations": 12, "citedby_url": "https://scholar.google.com/scholar?oi=bibs&hl=en&cites=16444851468414257757", "cites_id": ["16444851468414257757"], "public_access": null}, {"container_type": "Publication", "source": "AUTHOR_PUBLICATION_ENTRY", "bib": {"title": "Innovationspotenzialanalyse f\u00fcr die neuen Technologien f\u00fcr das Verwalten und Analysieren von gro\u00dfen Datenmengen (Big Data Management)", "pub_year": "2013", "citation": "Bundesministerium f\u00fcr Wirtschaft und Technologie, 2013"}, "filled": false, "author_pub_id": "am2ohp0AAAAJ:u9iWguZQMMsC", "num_citations": 12, "citedby_url": "https://scholar.google.com/scholar?oi=bibs&hl=en&cites=8147731848263799240", "cites_id": ["8147731848263799240"], "public_access": null}, {"container_type": "Publication", "source": "AUTHOR_PUBLICATION_ENTRY", "bib": {"title": "Robust named entity recognition in idiosyncratic domains", "pub_year": "2016", "citation": "arXiv preprint arXiv:1608.06757, 2016"}, "filled": false, "author_pub_id": "am2ohp0AAAAJ:1sJd4Hv_s6UC", "num_citations": 11, "citedby_url": "https://scholar.google.com/scholar?oi=bibs&hl=en&cites=6494226722778622370", "cites_id": ["6494226722778622370"], "public_access": null}, {"container_type": "Publication", "source": "AUTHOR_PUBLICATION_ENTRY", "bib": {"title": "INDREX: In-database relation extraction", "pub_year": "2015", "citation": "Information Systems 53, 124-144, 2015"}, "filled": false, "author_pub_id": "am2ohp0AAAAJ:ZHo1McVdvXMC", "num_citations": 11, "citedby_url": "https://scholar.google.com/scholar?oi=bibs&hl=en&cites=17766362138898247738", "cites_id": ["17766362138898247738"], "public_access": null}, {"container_type": "Publication", "source": "AUTHOR_PUBLICATION_ENTRY", "bib": {"title": "FactCrawl: A Fact Retrieval Framework for Full-Text Indices.", "pub_year": "2011", "citation": "WebDB, 2011"}, "filled": false, "author_pub_id": "am2ohp0AAAAJ:hqOjcs7Dif8C", "num_citations": 11, "citedby_url": "https://scholar.google.com/scholar?oi=bibs&hl=en&cites=14119583889404396359", "cites_id": ["14119583889404396359"], "public_access": null}, {"container_type": "Publication", "source": "AUTHOR_PUBLICATION_ENTRY", "bib": {"title": "Augmenting tables by self-supervised web search", "pub_year": "2010", "citation": "International Workshop on Business Intelligence for the Real-Time Enterprise \u2026, 2010"}, "filled": false, "author_pub_id": "am2ohp0AAAAJ:_FxGoFyzp5QC", "num_citations": 11, "citedby_url": "https://scholar.google.com/scholar?oi=bibs&hl=en&cites=7818515766066731669", "cites_id": ["7818515766066731669"], "public_access": null}, {"container_type": "Publication", "source": "AUTHOR_PUBLICATION_ENTRY", "bib": {"title": "Taxonomy-based routing overlays in p2p networks", "pub_year": "2004", "citation": "Proceedings. International Database Engineering and Applications Symposium \u2026, 2004"}, "filled": false, "author_pub_id": "am2ohp0AAAAJ:a0OBvERweLwC", "num_citations": 11, "citedby_url": "https://scholar.google.com/scholar?oi=bibs&hl=en&cites=17784905300582424775", "cites_id": ["17784905300582424775"], "public_access": null}, {"container_type": "Publication", "source": "AUTHOR_PUBLICATION_ENTRY", "bib": {"title": "Learning contextualized document representations for healthcare answer retrieval", "pub_year": "2020", "citation": "Proceedings of The Web Conference 2020, 1332-1343, 2020"}, "filled": false, "author_pub_id": "am2ohp0AAAAJ:t6usbXjVLHcC", "num_citations": 10, "citedby_url": "https://scholar.google.com/scholar?oi=bibs&hl=en&cites=10136114656209506606", "cites_id": ["10136114656209506606"], "public_access": null}, {"container_type": "Publication", "source": "AUTHOR_PUBLICATION_ENTRY", "bib": {"title": "How to model semantic peer-to-peer overlays?", "pub_year": "2006", "citation": "INFORMATIK 2006\u2013Informatik f\u00fcr Menschen, Band 1, 2006"}, "filled": false, "author_pub_id": "am2ohp0AAAAJ:NaGl4SEjCO4C", "num_citations": 10, "citedby_url": "https://scholar.google.com/scholar?oi=bibs&hl=en&cites=4971736649475361932", "cites_id": ["4971736649475361932"], "public_access": null}, {"container_type": "Publication", "source": "AUTHOR_PUBLICATION_ENTRY", "bib": {"title": "Classification algorithms for relation prediction", "pub_year": "2011", "citation": "2011 IEEE 27th International Conference on Data Engineering Workshops, 46-52, 2011"}, "filled": false, "author_pub_id": "am2ohp0AAAAJ:j3f4tGmQtD8C", "num_citations": 8, "citedby_url": "https://scholar.google.com/scholar?oi=bibs&hl=en&cites=16716074225984076515", "cites_id": ["16716074225984076515"], "public_access": null}, {"container_type": "Publication", "source": "AUTHOR_PUBLICATION_ENTRY", "bib": {"title": "What's the Intention Behind Your Query? A few Observations From a Large Developer Community.", "pub_year": "2008", "citation": "IRSW, 2008"}, "filled": false, "author_pub_id": "am2ohp0AAAAJ:KlAtU1dfN6UC", "num_citations": 7, "citedby_url": "https://scholar.google.com/scholar?oi=bibs&hl=en&cites=8337580466729202912", "cites_id": ["8337580466729202912"], "public_access": null}, {"container_type": "Publication", "source": "AUTHOR_PUBLICATION_ENTRY", "bib": {"title": "Smart-MD: neural paragraph retrieval of medical topics", "pub_year": "2018", "citation": "Companion Proceedings of the The Web Conference 2018, 203-206, 2018"}, "filled": false, "author_pub_id": "am2ohp0AAAAJ:738O_yMBCRsC", "num_citations": 6, "citedby_url": "https://scholar.google.com/scholar?oi=bibs&hl=en&cites=3532678191615077419", "cites_id": ["3532678191615077419"], "public_access": true}, {"container_type": "Publication", "source": "AUTHOR_PUBLICATION_ENTRY", "bib": {"title": "Ad-Hoc Queries over Document Collections\u2013A Case Study", "pub_year": "2009", "citation": "International Workshop on Business Intelligence for the Real-Time Enterprise \u2026, 2009"}, "filled": false, "author_pub_id": "am2ohp0AAAAJ:Wp0gIr-vW9MC", "num_citations": 6, "citedby_url": "https://scholar.google.com/scholar?oi=bibs&hl=en&cites=16823148438280271996", "cites_id": ["16823148438280271996"], "public_access": null}, {"container_type": "Publication", "source": "AUTHOR_PUBLICATION_ENTRY", "bib": {"title": "Robust recognition of complex entities in text exploiting enterprise data and NLP-techniques", "pub_year": "2008", "citation": "2008 Third International Conference on Digital Information Management, 551-558, 2008"}, "filled": false, "author_pub_id": "am2ohp0AAAAJ:_Qo2XoVZTnwC", "num_citations": 6, "citedby_url": "https://scholar.google.com/scholar?oi=bibs&hl=en&cites=18295962942622046928", "cites_id": ["18295962942622046928"], "public_access": null}, {"container_type": "Publication", "source": "AUTHOR_PUBLICATION_ENTRY", "bib": {"title": "Adaptive Overlays in Peer-to-Peer Netzwerken", "pub_year": "2005", "citation": ""}, "filled": false, "author_pub_id": "am2ohp0AAAAJ:LkGwnXOMwfcC", "num_citations": 6, "citedby_url": "https://scholar.google.com/scholar?oi=bibs&hl=en&cites=2725666500299023421", "cites_id": ["2725666500299023421"], "public_access": null}, {"container_type": "Publication", "source": "AUTHOR_PUBLICATION_ENTRY", "bib": {"title": "IDEL: In-database neural entity linking", "pub_year": "2019", "citation": "2019 IEEE International Conference on Big Data and Smart Computing (BigComp \u2026, 2019"}, "filled": false, "author_pub_id": "am2ohp0AAAAJ:V3AGJWp-ZtQC", "num_citations": 5, "citedby_url": "https://scholar.google.com/scholar?oi=bibs&hl=en&cites=11130439594141323097", "cites_id": ["11130439594141323097"], "public_access": false}, {"container_type": "Publication", "source": "AUTHOR_PUBLICATION_ENTRY", "bib": {"title": "FashionBrain Project: A Vision for Understanding Europe's Fashion Data Universe", "pub_year": "2017", "citation": "arXiv preprint arXiv:1710.09788, 2017"}, "filled": false, "author_pub_id": "am2ohp0AAAAJ:OU6Ihb5iCvQC", "num_citations": 5, "citedby_url": "https://scholar.google.com/scholar?oi=bibs&hl=en&cites=11856067241522614811", "cites_id": ["11856067241522614811"], "public_access": null}, {"container_type": "Publication", "source": "AUTHOR_PUBLICATION_ENTRY", "bib": {"title": "Discovering biased news articles leveraging multiple human annotations", "pub_year": "2020", "citation": "Proceedings of the 12th Language Resources and Evaluation Conference, 1268-1277, 2020"}, "filled": false, "author_pub_id": "am2ohp0AAAAJ:Mojj43d5GZwC", "num_citations": 4, "citedby_url": "https://scholar.google.com/scholar?oi=bibs&hl=en&cites=15801988032395206216", "cites_id": ["15801988032395206216"], "public_access": null}, {"container_type": "Publication", "source": "AUTHOR_PUBLICATION_ENTRY", "bib": {"title": "Interactive Relation Extraction in Main Memory Database Systems", "pub_year": "2016", "citation": "Proceedings of COLING 2016, the 26th International Conference on \u2026, 2016"}, "filled": false, "author_pub_id": "am2ohp0AAAAJ:SP6oXDckpogC", "num_citations": 4, "citedby_url": "https://scholar.google.com/scholar?oi=bibs&hl=en&cites=11340813412919481248", "cites_id": ["11340813412919481248"], "public_access": null}, {"container_type": "Publication", "source": "AUTHOR_PUBLICATION_ENTRY", "bib": {"title": "Beyond search: Retrieving complete tuples from a text-database", "pub_year": "2013", "citation": "Information Systems Frontiers 15 (3), 311-329, 2013"}, "filled": false, "author_pub_id": "am2ohp0AAAAJ:-f6ydRqryjwC", "num_citations": 4, "citedby_url": "https://scholar.google.com/scholar?oi=bibs&hl=en&cites=10612823492399416850", "cites_id": ["10612823492399416850"], "public_access": null}, {"container_type": "Publication", "source": "AUTHOR_PUBLICATION_ENTRY", "bib": {"title": "Fact-aware document retrieval for information extraction", "pub_year": "2012", "citation": "Datenbank-Spektrum 12 (2), 89-100, 2012"}, "filled": false, "author_pub_id": "am2ohp0AAAAJ:mVmsd5A6BfQC", "num_citations": 4, "citedby_url": "https://scholar.google.com/scholar?oi=bibs&hl=en&cites=7763616497625112320", "cites_id": ["7763616497625112320"], "public_access": null}, {"container_type": "Publication", "source": "AUTHOR_PUBLICATION_ENTRY", "bib": {"title": "Self-supervised Web search for any-k complete tuples", "pub_year": "2011", "citation": "Proceedings of the 2nd International Workshop on Business intelligencE and \u2026, 2011"}, "filled": false, "author_pub_id": "am2ohp0AAAAJ:5nxA0vEk-isC", "num_citations": 4, "citedby_url": "https://scholar.google.com/scholar?oi=bibs&hl=en&cites=1765422837149959158", "cites_id": ["1765422837149959158"], "public_access": null}, {"container_type": "Publication", "source": "AUTHOR_PUBLICATION_ENTRY", "bib": {"title": "Searching navigational pages in an intranet", "pub_year": "2009", "citation": "US Patent App. 12/022,777, 2009"}, "filled": false, "author_pub_id": "am2ohp0AAAAJ:qUcmZB5y_30C", "num_citations": 4, "citedby_url": "https://scholar.google.com/scholar?oi=bibs&hl=en&cites=18384592867909551564", "cites_id": ["18384592867909551564"], "public_access": null}, {"container_type": "Publication", "source": "AUTHOR_PUBLICATION_ENTRY", "bib": {"title": "Mapping enterprise entities to text segments", "pub_year": "2008", "citation": "Proceedings of the 2nd PhD workshop on Information and knowledge management \u2026, 2008"}, "filled": false, "author_pub_id": "am2ohp0AAAAJ:UebtZRa9Y70C", "num_citations": 4, "citedby_url": "https://scholar.google.com/scholar?oi=bibs&hl=en&cites=9379567130440496294", "cites_id": ["9379567130440496294"], "public_access": null}, {"container_type": "Publication", "source": "AUTHOR_PUBLICATION_ENTRY", "bib": {"title": "Assertion Detection in Clinical Notes: Medical Language Models to the Rescue?", "pub_year": "2021", "citation": "Proceedings of the Second Workshop on Natural Language Processing for \u2026, 2021"}, "filled": false, "author_pub_id": "am2ohp0AAAAJ:9vf0nzSNQJEC", "num_citations": 3, "citedby_url": "https://scholar.google.com/scholar?oi=bibs&hl=en&cites=12537552279636498594", "cites_id": ["12537552279636498594"], "public_access": null}, {"container_type": "Publication", "source": "AUTHOR_PUBLICATION_ENTRY", "bib": {"title": "Integrierte Versorgung chronisch kranker Patienten am Beispiel von MACSS", "pub_year": "2018", "citation": "IT f\u00fcr soziale Inklusion, 41-50, 2018"}, "filled": false, "author_pub_id": "am2ohp0AAAAJ:wbdj-CoPYUoC", "num_citations": 3, "citedby_url": "https://scholar.google.com/scholar?oi=bibs&hl=en&cites=10845359654275264989", "cites_id": ["10845359654275264989"], "public_access": null}, {"container_type": "Publication", "source": "AUTHOR_PUBLICATION_ENTRY", "bib": {"title": "Crowd-labeling fashion reviews with quality control", "pub_year": "2018", "citation": "arXiv preprint arXiv:1805.09648, 2018"}, "filled": false, "author_pub_id": "am2ohp0AAAAJ:K3LRdlH-MEoC", "num_citations": 3, "citedby_url": "https://scholar.google.com/scholar?oi=bibs&hl=en&cites=13048729384930359076", "cites_id": ["13048729384930359076"], "public_access": null}, {"container_type": "Publication", "source": "AUTHOR_PUBLICATION_ENTRY", "bib": {"title": "Resolving common analytical tasks in text databases", "pub_year": "2015", "citation": "Proceedings of the ACM Eighteenth International Workshop on Data Warehousing \u2026, 2015"}, "filled": false, "author_pub_id": "am2ohp0AAAAJ:D03iK_w7-QYC", "num_citations": 3, "citedby_url": "https://scholar.google.com/scholar?oi=bibs&hl=en&cites=1960423443851678123", "cites_id": ["1960423443851678123"], "public_access": null}, {"container_type": "Publication", "source": "AUTHOR_PUBLICATION_ENTRY", "bib": {"title": "INDREX: in-database distributional relation extraction", "pub_year": "2013", "citation": "Proceedings of the sixteenth international workshop on Data warehousing and \u2026, 2013"}, "filled": false, "author_pub_id": "am2ohp0AAAAJ:maZDTaKrznsC", "num_citations": 3, "citedby_url": "https://scholar.google.com/scholar?oi=bibs&hl=en&cites=9595422146067301531", "cites_id": ["9595422146067301531"], "public_access": null}, {"container_type": "Publication", "source": "AUTHOR_PUBLICATION_ENTRY", "bib": {"title": "Beyond search: Web-scale business analytics", "pub_year": "2009", "citation": "International Conference on Web Information Systems Engineering, 5-5, 2009"}, "filled": false, "author_pub_id": "am2ohp0AAAAJ:Se3iqnhoufwC", "num_citations": 3, "citedby_url": "https://scholar.google.com/scholar?oi=bibs&hl=en&cites=7685617849249311659", "cites_id": ["7685617849249311659"], "public_access": null}, {"container_type": "Publication", "source": "AUTHOR_PUBLICATION_ENTRY", "bib": {"title": "What Do You See in this Patient? Behavioral Testing of Clinical NLP Models", "pub_year": "2021", "citation": "arXiv preprint arXiv:2111.15512, 2021"}, "filled": false, "author_pub_id": "am2ohp0AAAAJ:ZuybSZzF8UAC", "num_citations": 2, "citedby_url": "https://scholar.google.com/scholar?oi=bibs&hl=en&cites=13365309263981803588", "cites_id": ["13365309263981803588"], "public_access": null}, {"container_type": "Publication", "source": "AUTHOR_PUBLICATION_ENTRY", "bib": {"title": "Self-supervised answer retrieval on clinical notes", "pub_year": "2021", "citation": "arXiv preprint arXiv:2108.00775, 2021"}, "filled": false, "author_pub_id": "am2ohp0AAAAJ:LjlpjdlvIbIC", "num_citations": 2, "citedby_url": "https://scholar.google.com/scholar?oi=bibs&hl=en&cites=3751079929033408049", "cites_id": ["3751079929033408049"], "public_access": null}, {"container_type": "Publication", "source": "AUTHOR_PUBLICATION_ENTRY", "bib": {"title": "Aspect-based passage retrieval with contextualized discourse vectors", "pub_year": "2021", "citation": "European Conference on Information Retrieval, 537-542, 2021"}, "filled": false, "author_pub_id": "am2ohp0AAAAJ:5awf1xo2G04C", "num_citations": 2, "citedby_url": "https://scholar.google.com/scholar?oi=bibs&hl=en&cites=15753520555318350234", "cites_id": ["15753520555318350234"], "public_access": null}, {"container_type": "Publication", "source": "AUTHOR_PUBLICATION_ENTRY", "bib": {"title": "2.1 Kommerzielle Datenm\u00e4rkte", "pub_year": "2021", "citation": "Forschungsdaten-management, 147, 2021"}, "filled": false, "author_pub_id": "am2ohp0AAAAJ:Y5dfb0dijaUC", "num_citations": 2, "citedby_url": "https://scholar.google.com/scholar?oi=bibs&hl=en&cites=6252050295438420704", "cites_id": ["6252050295438420704"], "public_access": null}, {"container_type": "Publication", "source": "AUTHOR_PUBLICATION_ENTRY", "bib": {"title": "Neuartige Kommunikationswege und Strukturen zur Optimierung der h\u00e4uslichen Versorgung am Beispiel von nierentransplantierten Patienten", "pub_year": "2019", "citation": "Digitale Transformation von Dienstleistungen im Gesundheitswesen VI, 407-421, 2019"}, "filled": false, "author_pub_id": "am2ohp0AAAAJ:1qzjygNMrQYC", "num_citations": 2, "citedby_url": "https://scholar.google.com/scholar?oi=bibs&hl=en&cites=1420544451232434222", "cites_id": ["1420544451232434222"], "public_access": null}, {"container_type": "Publication", "source": "AUTHOR_PUBLICATION_ENTRY", "bib": {"title": "Web 2.0 Business Analytics.", "pub_year": "2008", "citation": "Datenbank-Spektrum 8 (25), 4-11, 2008"}, "filled": false, "author_pub_id": "am2ohp0AAAAJ:0EnyYjriUFMC", "num_citations": 2, "citedby_url": "https://scholar.google.com/scholar?oi=bibs&hl=en&cites=1690875088716658292", "cites_id": ["1690875088716658292"], "public_access": null}, {"container_type": "Publication", "source": "AUTHOR_PUBLICATION_ENTRY", "bib": {"title": "A concept for flexible event-driven invocation of distributed service compositions", "pub_year": "2007", "citation": "27th International Conference on Distributed Computing Systems Workshops \u2026, 2007"}, "filled": false, "author_pub_id": "am2ohp0AAAAJ:yD5IFk8b50cC", "num_citations": 2, "citedby_url": "https://scholar.google.com/scholar?oi=bibs&hl=en&cites=3448765851932768146", "cites_id": ["3448765851932768146"], "public_access": null}, {"container_type": "Publication", "source": "AUTHOR_PUBLICATION_ENTRY", "bib": {"title": "Challenges and Trends in Information Management.", "pub_year": "2006", "citation": "Datenbank-Spektrum 19, 15-22, 2006"}, "filled": false, "author_pub_id": "am2ohp0AAAAJ:8k81kl-MbHgC", "num_citations": 2, "citedby_url": "https://scholar.google.com/scholar?oi=bibs&hl=en&cites=4566525379281661084", "cites_id": ["4566525379281661084"], "public_access": null}, {"container_type": "Publication", "source": "AUTHOR_PUBLICATION_ENTRY", "bib": {"title": "Cross-Lingual Knowledge Transfer for Clinical Phenotyping", "pub_year": "2022", "citation": "arXiv preprint arXiv:2208.01912, 2022"}, "filled": false, "author_pub_id": "am2ohp0AAAAJ:UHK10RUVsp4C", "num_citations": 1, "citedby_url": "https://scholar.google.com/scholar?oi=bibs&hl=en&cites=9655913150580300328", "cites_id": ["9655913150580300328"], "public_access": null}, {"container_type": "Publication", "source": "AUTHOR_PUBLICATION_ENTRY", "bib": {"title": "TrainX\u2013Named Entity Linking with Active Sampling and Bi-Encoders", "pub_year": "2020", "citation": "Proceedings of the 28th International Conference on Computational \u2026, 2020"}, "filled": false, "author_pub_id": "am2ohp0AAAAJ:eMMeJKvmdy0C", "num_citations": 1, "citedby_url": "https://scholar.google.com/scholar?oi=bibs&hl=en&cites=16120255849805140714", "cites_id": ["16120255849805140714"], "public_access": null}, {"container_type": "Publication", "source": "AUTHOR_PUBLICATION_ENTRY", "bib": {"title": "Is language modeling enough? Evaluating effective embedding combinations", "pub_year": "2020", "citation": ""}, "filled": false, "author_pub_id": "am2ohp0AAAAJ:HE397vMXCloC", "num_citations": 1, "citedby_url": "https://scholar.google.com/scholar?oi=bibs&hl=en&cites=3249584961698203355", "cites_id": ["3249584961698203355"], "public_access": true}, {"container_type": "Publication", "source": "AUTHOR_PUBLICATION_ENTRY", "bib": {"title": "RelVis: Benchmarking OpenIE Systems.", "pub_year": "2017", "citation": "ISWC (Posters, Demos & Industry Tracks), 2017"}, "filled": false, "author_pub_id": "am2ohp0AAAAJ:p2g8aNsByqUC", "num_citations": 1, "citedby_url": "https://scholar.google.com/scholar?oi=bibs&hl=en&cites=6455428165122813836", "cites_id": ["6455428165122813836"], "public_access": true}, {"container_type": "Publication", "source": "AUTHOR_PUBLICATION_ENTRY", "bib": {"title": "Integrierte Versorgung nierentransplantierter Patienten", "pub_year": "2016", "citation": "Dialyse aktuell 20 (06), 285-290, 2016"}, "filled": false, "author_pub_id": "am2ohp0AAAAJ:J-pR_7NvFogC", "num_citations": 1, "citedby_url": "https://scholar.google.com/scholar?oi=bibs&hl=en&cites=10426766046289910053", "cites_id": ["10426766046289910053"], "public_access": null}, {"container_type": "Publication", "source": "AUTHOR_PUBLICATION_ENTRY", "bib": {"title": "A marketplace for web scale analytics and text annotation services", "pub_year": "2014", "citation": "Proceedings of COLING 2014, the 25th International Conference on \u2026, 2014"}, "filled": false, "author_pub_id": "am2ohp0AAAAJ:SeFeTyx0c_EC", "num_citations": 1, "citedby_url": "https://scholar.google.com/scholar?oi=bibs&hl=en&cites=9184180870666634814", "cites_id": ["9184180870666634814"], "public_access": null}, {"container_type": "Publication", "source": "AUTHOR_PUBLICATION_ENTRY", "bib": {"title": "Classification Algorithms for Web Text Filtering", "pub_year": "2011", "citation": "DaLi Workshop at ICDE, 2011"}, "filled": false, "author_pub_id": "am2ohp0AAAAJ:2P1L_qKh6hAC", "num_citations": 1, "citedby_url": "https://scholar.google.com/scholar?oi=bibs&hl=en&cites=11233814528040278313", "cites_id": ["11233814528040278313"], "public_access": null}, {"container_type": "Publication", "source": "AUTHOR_PUBLICATION_ENTRY", "bib": {"title": "This Patient Looks Like That Patient: Prototypical Networks for Interpretable Diagnosis Prediction from Clinical Text", "pub_year": "2022", "citation": "arXiv preprint arXiv:2210.08500, 2022"}, "filled": false, "author_pub_id": "am2ohp0AAAAJ:uLbwQdceFCQC", "num_citations": 0, "citedby_url": null, "cites_id": null, "public_access": null}, {"container_type": "Publication", "source": "AUTHOR_PUBLICATION_ENTRY", "bib": {"title": "Attention Networks for Augmenting Clinical Text with Support Sets for Diagnosis Prediction", "pub_year": "2022", "citation": "Proceedings of the 29th International Conference on Computational \u2026, 2022"}, "filled": false, "author_pub_id": "am2ohp0AAAAJ:JQOojiI6XY0C", "num_citations": 0, "citedby_url": null, "cites_id": null, "public_access": null}, {"container_type": "Publication", "source": "AUTHOR_PUBLICATION_ENTRY", "bib": {"title": "KIMERA: Injecting Domain Knowledge into Vacant Transformer Heads", "pub_year": "2022", "citation": "Proceedings of the Thirteenth Language Resources and Evaluation Conference \u2026, 2022"}, "filled": false, "author_pub_id": "am2ohp0AAAAJ:1yQoGdGgb4wC", "num_citations": 0, "citedby_url": null, "cites_id": null, "public_access": null}, {"container_type": "Publication", "source": "AUTHOR_PUBLICATION_ENTRY", "bib": {"title": "From Symmetry to Asymmetry: Generalizing TSP Approximations by Parametrization", "pub_year": "2021", "citation": "International Symposium on Fundamentals of Computation Theory, 53-66, 2021"}, "filled": false, "author_pub_id": "am2ohp0AAAAJ:PR6Y55bgFSsC", "num_citations": 0, "citedby_url": null, "cites_id": null, "public_access": null}, {"container_type": "Publication", "source": "AUTHOR_PUBLICATION_ENTRY", "bib": {"title": "1 \u201cNeural Machine Reading for Domain-Specific Text Resources\u201d von Sebastian Arnold, Universit\u00e9 de Fribourg, Schweiz, Oct. 2020", "pub_year": "2020", "citation": ""}, "filled": false, "author_pub_id": "am2ohp0AAAAJ:hkOj_22Ku90C", "num_citations": 0, "citedby_url": null, "cites_id": null, "public_access": null}, {"container_type": "Publication", "source": "AUTHOR_PUBLICATION_ENTRY", "bib": {"title": "Beyond search: business analytics on text data", "pub_year": "2013", "citation": "Berlin, Technische Universit\u00e4t Berlin, Habil.-Schr., 2013, 2013"}, "filled": false, "author_pub_id": "am2ohp0AAAAJ:cFHS6HbyZ2cC", "num_citations": 0, "citedby_url": null, "cites_id": null, "public_access": null}, {"container_type": "Publication", "source": "AUTHOR_PUBLICATION_ENTRY", "bib": {"title": "User Interaktion", "pub_year": "2011", "citation": ""}, "filled": false, "author_pub_id": "am2ohp0AAAAJ:70eg2SAEIzsC", "num_citations": 0, "citedby_url": null, "cites_id": null, "public_access": null}, {"container_type": "Publication", "source": "AUTHOR_PUBLICATION_ENTRY", "bib": {"title": "Group summary-Mining for social serendipity", "pub_year": "2008", "citation": "Dagstuhl Seminar Proceedings 8391, 1-11, 2008"}, "filled": false, "author_pub_id": "am2ohp0AAAAJ:JoZmwDi-zQgC", "num_citations": 0, "citedby_url": null, "cites_id": null, "public_access": null}, {"container_type": "Publication", "source": "AUTHOR_PUBLICATION_ENTRY", "bib": {"title": "08391 Group Summary--Mining for Social Serendipity", "pub_year": "2008", "citation": "Dagstuhl Seminar Proceedings, 2008"}, "filled": false, "author_pub_id": "am2ohp0AAAAJ:pyW8ca7W8N0C", "num_citations": 0, "citedby_url": null, "cites_id": null, "public_access": null}, {"container_type": "Publication", "source": "AUTHOR_PUBLICATION_ENTRY", "bib": {"title": "Mediation in the Context of a Peer-to-Peer Network", "pub_year": "2003", "citation": "Info Lunch, Learning Lab Lower Saxony (L3S), Universit\u00e4t Hannover, 19.02. 2003, 2003"}, "filled": false, "author_pub_id": "am2ohp0AAAAJ:KxtntwgDAa4C", "num_citations": 0, "citedby_url": null, "cites_id": null, "public_access": null}, {"container_type": "Publication", "source": "AUTHOR_PUBLICATION_ENTRY", "bib": {"title": "Document Information", "pub_year": null, "citation": ""}, "filled": false, "author_pub_id": "am2ohp0AAAAJ:tOudhMTPpwUC", "num_citations": 0, "citedby_url": null, "cites_id": null, "public_access": null}, {"container_type": "Publication", "source": "AUTHOR_PUBLICATION_ENTRY", "bib": {"title": "A Query Planner for Executing Structured Queries over Document Collections", "pub_year": null, "citation": ""}, "filled": false, "author_pub_id": "am2ohp0AAAAJ:HoB7MX3m0LUC", "num_citations": 0, "citedby_url": null, "cites_id": null, "public_access": null}, {"container_type": "Publication", "source": "AUTHOR_PUBLICATION_ENTRY", "bib": {"title": "1st International Workshop on Managing Data Throughout its Lifecycle (DaLi 2011)", "pub_year": null, "citation": ""}, "filled": false, "author_pub_id": "am2ohp0AAAAJ:pqnbT2bcN3wC", "num_citations": 0, "citedby_url": null, "cites_id": null, "public_access": null}, {"container_type": "Publication", "source": "AUTHOR_PUBLICATION_ENTRY", "bib": {"title": "Extraktion komplexer Relationen aus englischsprachigen Webseiten", "pub_year": null, "citation": ""}, "filled": false, "author_pub_id": "am2ohp0AAAAJ:35N4QoGY0k4C", "num_citations": 0, "citedby_url": null, "cites_id": null, "public_access": null}], "public_access": {"available": 7, "not_available": 1}}